{"img": {"height": 1478, "width": 1108, "image_path": "train_0039.png"}, "document": [{"id": 0, "box": [162, 876, 527, 918], "bndbox": [[162, 881], [527, 876], [527, 913], [162, 918]], "text": "H COUPLE SEA", "words": [{"id": 0, "box": [162, 880, 192, 918], "bndbox": [[162, 881], [192, 880], [192, 917], [162, 918]], "text": "H"}, {"id": 1, "box": [192, 880, 223, 917], "bndbox": [[192, 880], [223, 880], [223, 917], [192, 917]], "text": " "}, {"id": 2, "box": [223, 879, 254, 917], "bndbox": [[223, 880], [254, 879], [254, 916], [223, 917]], "text": "C"}, {"id": 3, "box": [254, 879, 285, 916], "bndbox": [[254, 879], [285, 879], [285, 916], [254, 916]], "text": "O"}, {"id": 4, "box": [285, 878, 316, 916], "bndbox": [[285, 879], [316, 878], [316, 915], [285, 916]], "text": "U"}, {"id": 5, "box": [316, 878, 344, 915], "bndbox": [[316, 878], [344, 878], [344, 915], [316, 915]], "text": "P"}, {"id": 6, "box": [344, 878, 375, 915], "bndbox": [[344, 878], [375, 878], [375, 915], [344, 915]], "text": "L"}, {"id": 7, "box": [375, 877, 409, 915], "bndbox": [[375, 878], [409, 877], [409, 914], [375, 915]], "text": "E"}, {"id": 8, "box": [409, 877, 440, 914], "bndbox": [[409, 877], [440, 877], [440, 914], [409, 914]], "text": " "}, {"id": 9, "box": [440, 876, 468, 914], "bndbox": [[440, 877], [468, 876], [468, 913], [440, 914]], "text": "S"}, {"id": 10, "box": [468, 876, 499, 913], "bndbox": [[468, 876], [499, 876], [499, 913], [468, 913]], "text": "E"}, {"id": 11, "box": [499, 876, 527, 913], "bndbox": [[499, 876], [527, 876], [527, 913], [499, 913]], "text": "A"}]}, {"id": 1, "box": [715, 873, 889, 911], "bndbox": [[715, 873], [889, 873], [889, 911], [715, 911]], "text": "70,000", "words": [{"id": 12, "box": [715, 873, 740, 911], "bndbox": [[715, 873], [740, 873], [740, 911], [715, 911]], "text": "7"}, {"id": 13, "box": [740, 873, 769, 911], "bndbox": [[740, 873], [769, 873], [769, 911], [740, 911]], "text": "0"}, {"id": 14, "box": [769, 873, 802, 911], "bndbox": [[769, 873], [802, 873], [802, 911], [769, 911]], "text": ","}, {"id": 15, "box": [802, 873, 834, 911], "bndbox": [[802, 873], [834, 873], [834, 911], [802, 911]], "text": "0"}, {"id": 16, "box": [834, 873, 863, 911], "bndbox": [[834, 873], [863, 873], [863, 911], [834, 911]], "text": "0"}, {"id": 17, "box": [863, 873, 889, 911], "bndbox": [[863, 873], [889, 873], [889, 911], [863, 911]], "text": "0"}]}, {"id": 2, "box": [255, 928, 316, 975], "bndbox": [[255, 928], [316, 928], [316, 975], [255, 975]], "text": "TL", "words": [{"id": 18, "box": [255, 928, 285, 975], "bndbox": [[255, 928], [285, 928], [285, 975], [255, 975]], "text": "T"}, {"id": 19, "box": [285, 928, 316, 975], "bndbox": [[285, 928], [316, 928], [316, 975], [285, 975]], "text": "L"}]}, {"id": 3, "box": [256, 977, 383, 1026], "bndbox": [[256, 981], [381, 977], [383, 1022], [258, 1026]], "text": "CASH", "words": [{"id": 20, "box": [256, 979, 291, 1026], "bndbox": [[256, 981], [289, 979], [291, 1024], [258, 1026]], "text": "C"}, {"id": 21, "box": [289, 979, 320, 1024], "bndbox": [[289, 979], [318, 979], [320, 1024], [291, 1024]], "text": "A"}, {"id": 22, "box": [318, 978, 349, 1024], "bndbox": [[318, 979], [347, 978], [349, 1023], [320, 1024]], "text": "S"}, {"id": 23, "box": [347, 977, 383, 1023], "bndbox": [[347, 978], [381, 977], [383, 1022], [349, 1023]], "text": "H"}]}, {"id": 4, "box": [708, 973, 891, 1019], "bndbox": [[708, 976], [890, 973], [891, 1016], [709, 1019]], "text": "70,000", "words": [{"id": 24, "box": [708, 975, 741, 1019], "bndbox": [[708, 976], [740, 975], [741, 1018], [709, 1019]], "text": "7"}, {"id": 25, "box": [740, 974, 770, 1018], "bndbox": [[740, 975], [769, 974], [770, 1017], [741, 1018]], "text": "0"}, {"id": 26, "box": [769, 974, 800, 1017], "bndbox": [[769, 974], [799, 974], [800, 1017], [770, 1017]], "text": ","}, {"id": 27, "box": [799, 973, 832, 1017], "bndbox": [[799, 974], [831, 973], [832, 1016], [800, 1017]], "text": "0"}, {"id": 28, "box": [831, 973, 865, 1016], "bndbox": [[831, 973], [864, 973], [865, 1016], [832, 1016]], "text": "0"}, {"id": 29, "box": [864, 973, 891, 1016], "bndbox": [[864, 973], [890, 973], [891, 1016], [865, 1016]], "text": "0"}]}], "uid": "train_0039", "label_entities": [{"entity_id": 0, "label": "menu.nm", "word_idx": [0, 1, 2, 3, 4, 5, 6, 7, 8, 9, 10, 11]}, {"entity_id": 1, "label": "menu.price", "word_idx": [12, 13, 14, 15, 16, 17]}, {"entity_id": 3, "label": "total.cashprice", "word_idx": [20, 21, 22, 23, 24, 25, 26, 27, 28, 29]}]}