{"img": {"height": 1296, "width": 864, "image_path": "train_0482.png"}, "document": [{"id": 0, "box": [552, 633, 747, 679], "bndbox": [[552, 637], [746, 633], [747, 675], [553, 679]], "text": "20,000", "words": [{"id": 0, "box": [552, 636, 601, 679], "bndbox": [[552, 637], [600, 636], [601, 678], [553, 679]], "text": "2"}, {"id": 1, "box": [600, 635, 625, 678], "bndbox": [[600, 636], [624, 635], [625, 677], [601, 678]], "text": "0"}, {"id": 2, "box": [624, 634, 653, 677], "bndbox": [[624, 635], [652, 634], [653, 676], [625, 677]], "text": ","}, {"id": 3, "box": [652, 634, 681, 676], "bndbox": [[652, 634], [680, 634], [681, 676], [653, 676]], "text": "0"}, {"id": 4, "box": [680, 633, 712, 676], "bndbox": [[680, 634], [711, 633], [712, 675], [681, 676]], "text": "0"}, {"id": 5, "box": [711, 633, 747, 675], "bndbox": [[711, 633], [746, 633], [747, 675], [712, 675]], "text": "0"}]}, {"id": 1, "box": [88, 644, 384, 685], "bndbox": [[88, 648], [383, 644], [384, 680], [88, 685]], "text": "THAI ICETEA", "words": [{"id": 6, "box": [88, 647, 109, 685], "bndbox": [[88, 648], [109, 647], [109, 684], [88, 685]], "text": "T"}, {"id": 7, "box": [109, 647, 137, 684], "bndbox": [[109, 647], [137, 647], [137, 684], [109, 684]], "text": "H"}, {"id": 8, "box": [137, 646, 168, 684], "bndbox": [[137, 647], [167, 646], [168, 683], [137, 684]], "text": "A"}, {"id": 9, "box": [167, 646, 199, 683], "bndbox": [[167, 646], [198, 646], [199, 683], [168, 683]], "text": "I"}, {"id": 10, "box": [198, 646, 223, 683], "bndbox": [[198, 646], [223, 646], [223, 682], [199, 683]], "text": " "}, {"id": 11, "box": [223, 645, 248, 682], "bndbox": [[223, 646], [247, 645], [248, 682], [223, 682]], "text": "I"}, {"id": 12, "box": [247, 645, 276, 682], "bndbox": [[247, 645], [275, 645], [276, 681], [248, 682]], "text": "C"}, {"id": 13, "box": [275, 645, 303, 681], "bndbox": [[275, 645], [303, 645], [303, 681], [276, 681]], "text": "E"}, {"id": 14, "box": [303, 644, 331, 681], "bndbox": [[303, 645], [330, 644], [331, 680], [303, 681]], "text": "T"}, {"id": 15, "box": [330, 644, 356, 680], "bndbox": [[330, 644], [355, 644], [356, 680], [331, 680]], "text": "E"}, {"id": 16, "box": [355, 644, 384, 680], "bndbox": [[355, 644], [383, 644], [384, 680], [356, 680]], "text": "A"}]}, {"id": 2, "box": [88, 691, 411, 733], "bndbox": [[88, 697], [410, 691], [411, 727], [88, 733]], "text": "ICE GREENTEA", "words": [{"id": 17, "box": [88, 696, 111, 733], "bndbox": [[88, 697], [111, 696], [111, 732], [88, 733]], "text": "I"}, {"id": 18, "box": [111, 696, 138, 732], "bndbox": [[111, 696], [138, 696], [138, 732], [111, 732]], "text": "C"}, {"id": 19, "box": [138, 695, 165, 732], "bndbox": [[138, 696], [165, 695], [165, 731], [138, 732]], "text": "E"}, {"id": 20, "box": [165, 695, 195, 731], "bndbox": [[165, 695], [195, 695], [195, 731], [165, 731]], "text": " "}, {"id": 21, "box": [195, 694, 222, 731], "bndbox": [[195, 695], [222, 694], [222, 730], [195, 731]], "text": "G"}, {"id": 22, "box": [222, 694, 249, 730], "bndbox": [[222, 694], [249, 694], [249, 730], [222, 730]], "text": "R"}, {"id": 23, "box": [249, 693, 276, 730], "bndbox": [[249, 694], [275, 693], [276, 729], [249, 730]], "text": "E"}, {"id": 24, "box": [275, 693, 303, 729], "bndbox": [[275, 693], [302, 693], [303, 729], [276, 729]], "text": "E"}, {"id": 25, "box": [302, 692, 330, 729], "bndbox": [[302, 693], [329, 692], [330, 728], [303, 729]], "text": "N"}, {"id": 26, "box": [329, 692, 357, 728], "bndbox": [[329, 692], [356, 692], [357, 728], [330, 728]], "text": "T"}, {"id": 27, "box": [356, 691, 384, 728], "bndbox": [[356, 692], [383, 691], [384, 727], [357, 728]], "text": "E"}, {"id": 28, "box": [383, 691, 411, 727], "bndbox": [[383, 691], [410, 691], [411, 727], [384, 727]], "text": "A"}]}, {"id": 3, "box": [553, 686, 747, 726], "bndbox": [[553, 689], [746, 686], [747, 723], [554, 726]], "text": "22,000", "words": [{"id": 29, "box": [553, 688, 603, 726], "bndbox": [[553, 689], [602, 688], [603, 725], [554, 726]], "text": "2"}, {"id": 30, "box": [602, 687, 631, 725], "bndbox": [[602, 688], [630, 687], [631, 724], [603, 725]], "text": "2"}, {"id": 31, "box": [630, 687, 659, 724], "bndbox": [[630, 687], [658, 687], [659, 724], [631, 724]], "text": ","}, {"id": 32, "box": [658, 686, 690, 724], "bndbox": [[658, 687], [689, 686], [690, 723], [659, 724]], "text": "0"}, {"id": 33, "box": [689, 686, 718, 723], "bndbox": [[689, 686], [717, 686], [718, 723], [690, 723]], "text": "0"}, {"id": 34, "box": [717, 686, 747, 723], "bndbox": [[717, 686], [746, 686], [747, 723], [718, 723]], "text": "0"}]}, {"id": 4, "box": [167, 742, 221, 783], "bndbox": [[167, 742], [221, 742], [221, 783], [167, 783]], "text": "TL", "words": [{"id": 35, "box": [167, 742, 190, 783], "bndbox": [[167, 742], [190, 742], [190, 783], [167, 783]], "text": "T"}, {"id": 36, "box": [190, 742, 221, 783], "bndbox": [[190, 742], [221, 742], [221, 783], [190, 783]], "text": "L"}]}, {"id": 5, "box": [382, 736, 743, 775], "bndbox": [[382, 739], [742, 736], [743, 772], [382, 775]], "text": "42.000", "words": [{"id": 37, "box": [382, 738, 466, 775], "bndbox": [[382, 739], [465, 738], [466, 774], [382, 775]], "text": "4"}, {"id": 38, "box": [465, 737, 517, 774], "bndbox": [[465, 738], [517, 737], [517, 773], [466, 774]], "text": "2"}, {"id": 39, "box": [517, 737, 574, 773], "bndbox": [[517, 737], [574, 737], [574, 773], [517, 773]], "text": "."}, {"id": 40, "box": [574, 736, 634, 773], "bndbox": [[574, 737], [634, 736], [634, 772], [574, 773]], "text": "0"}, {"id": 41, "box": [634, 736, 691, 772], "bndbox": [[634, 736], [691, 736], [691, 772], [634, 772]], "text": "0"}, {"id": 42, "box": [691, 736, 743, 772], "bndbox": [[691, 736], [742, 736], [743, 772], [691, 772]], "text": "0"}]}, {"id": 6, "box": [164, 788, 281, 831], "bndbox": [[164, 791], [280, 788], [281, 827], [165, 831]], "text": "CASH", "words": [{"id": 43, "box": [164, 790, 195, 831], "bndbox": [[164, 791], [194, 790], [195, 829], [165, 831]], "text": "C"}, {"id": 44, "box": [194, 789, 223, 829], "bndbox": [[194, 790], [222, 789], [223, 829], [195, 829]], "text": "A"}, {"id": 45, "box": [222, 788, 250, 829], "bndbox": [[222, 789], [249, 788], [250, 828], [223, 829]], "text": "S"}, {"id": 46, "box": [249, 788, 281, 828], "bndbox": [[249, 788], [280, 788], [281, 827], [250, 828]], "text": "H"}]}, {"id": 7, "box": [557, 784, 752, 825], "bndbox": [[558, 784], [752, 787], [752, 825], [557, 822]], "text": "50,000", "words": [{"id": 47, "box": [557, 784, 604, 822], "bndbox": [[558, 784], [604, 784], [604, 822], [557, 822]], "text": "5"}, {"id": 48, "box": [604, 784, 633, 823], "bndbox": [[604, 784], [633, 785], [632, 823], [604, 822]], "text": "0"}, {"id": 49, "box": [632, 785, 661, 823], "bndbox": [[633, 785], [661, 785], [660, 823], [632, 823]], "text": ","}, {"id": 50, "box": [660, 785, 689, 824], "bndbox": [[661, 785], [689, 786], [689, 824], [660, 823]], "text": "0"}, {"id": 51, "box": [689, 786, 720, 824], "bndbox": [[689, 786], [720, 786], [720, 824], [689, 824]], "text": "0"}, {"id": 52, "box": [720, 786, 752, 825], "bndbox": [[720, 786], [752, 787], [752, 825], [720, 824]], "text": "0"}]}, {"id": 8, "box": [163, 837, 225, 882], "bndbox": [[163, 837], [225, 837], [225, 882], [163, 882]], "text": "CG", "words": [{"id": 53, "box": [163, 837, 194, 882], "bndbox": [[163, 837], [194, 837], [194, 882], [163, 882]], "text": "C"}, {"id": 54, "box": [194, 837, 225, 882], "bndbox": [[194, 837], [225, 837], [225, 882], [194, 882]], "text": "G"}]}, {"id": 9, "box": [583, 830, 755, 881], "bndbox": [[585, 830], [755, 838], [753, 881], [583, 873]], "text": "8,000", "words": [{"id": 55, "box": [583, 830, 638, 875], "bndbox": [[585, 830], [638, 832], [636, 875], [583, 873]], "text": "8"}, {"id": 56, "box": [636, 832, 666, 876], "bndbox": [[638, 832], [666, 833], [664, 876], [636, 875]], "text": ","}, {"id": 57, "box": [664, 833, 694, 878], "bndbox": [[666, 833], [694, 835], [692, 878], [664, 876]], "text": "0"}, {"id": 58, "box": [692, 835, 723, 879], "bndbox": [[694, 835], [723, 836], [721, 879], [692, 878]], "text": "0"}, {"id": 59, "box": [721, 836, 755, 881], "bndbox": [[723, 836], [755, 838], [753, 881], [721, 879]], "text": "0"}]}], "uid": "train_0482", "label_entities": [{"entity_id": 0, "label": "menu.nm", "word_idx": [6, 7, 8, 9, 10, 11, 12, 13, 14, 15, 16]}, {"entity_id": 1, "label": "menu.price", "word_idx": [0, 1, 2, 3, 4, 5]}, {"entity_id": 2, "label": "menu.nm", "word_idx": [17, 18, 19, 20, 21, 22, 23, 24, 25, 26, 27, 28]}, {"entity_id": 3, "label": "menu.price", "word_idx": [29, 30, 31, 32, 33, 34]}, {"entity_id": 4, "label": "total.total_price", "word_idx": [35, 36, 37, 38, 39, 40, 41, 42]}, {"entity_id": 5, "label": "total.cashprice", "word_idx": [43, 44, 45, 46, 47, 48, 49, 50, 51, 52]}, {"entity_id": 6, "label": "total.changeprice", "word_idx": [53, 54, 55, 56, 57, 58, 59]}]}