{"img": {"height": 864, "width": 576, "image_path": "train_0664.png"}, "document": [{"id": 0, "box": [88, 49, 482, 186], "bndbox": [[94, 49], [482, 69], [476, 186], [88, 166]], "text": "Dynamie", "words": [{"id": 0, "box": [88, 49, 171, 170], "bndbox": [[94, 49], [171, 53], [165, 170], [88, 166]], "text": "D"}, {"id": 1, "box": [165, 53, 220, 172], "bndbox": [[171, 53], [220, 55], [214, 172], [165, 170]], "text": "y"}, {"id": 2, "box": [214, 55, 258, 174], "bndbox": [[220, 55], [258, 57], [252, 174], [214, 172]], "text": "n"}, {"id": 3, "box": [252, 57, 326, 178], "bndbox": [[258, 57], [326, 61], [320, 178], [252, 174]], "text": "a"}, {"id": 4, "box": [320, 61, 394, 181], "bndbox": [[326, 61], [394, 64], [388, 181], [320, 178]], "text": "m"}, {"id": 5, "box": [388, 64, 433, 183], "bndbox": [[394, 64], [433, 66], [427, 183], [388, 181]], "text": "i"}, {"id": 6, "box": [427, 66, 482, 186], "bndbox": [[433, 66], [482, 69], [476, 186], [427, 183]], "text": "e"}]}, {"id": 1, "box": [440, 211, 476, 226], "bndbox": [[440, 211], [476, 211], [476, 226], [440, 226]], "text": "BEH", "words": [{"id": 7, "box": [440, 211, 452, 226], "bndbox": [[440, 211], [452, 211], [452, 226], [440, 226]], "text": "B"}, {"id": 8, "box": [452, 211, 465, 226], "bndbox": [[452, 211], [465, 211], [465, 226], [452, 226]], "text": "E"}, {"id": 9, "box": [465, 211, 476, 226], "bndbox": [[465, 211], [476, 211], [476, 226], [465, 226]], "text": "H"}]}, {"id": 2, "box": [65, 364, 194, 391], "bndbox": [[65, 364], [194, 364], [194, 391], [65, 391]], "text": "KEJU SUSU", "words": [{"id": 10, "box": [65, 364, 80, 391], "bndbox": [[65, 364], [80, 364], [80, 391], [65, 391]], "text": "K"}, {"id": 11, "box": [80, 364, 96, 391], "bndbox": [[80, 364], [96, 364], [96, 391], [80, 391]], "text": "E"}, {"id": 12, "box": [96, 364, 109, 391], "bndbox": [[96, 364], [109, 364], [109, 391], [96, 391]], "text": "J"}, {"id": 13, "box": [109, 364, 122, 391], "bndbox": [[109, 364], [122, 364], [122, 391], [109, 391]], "text": "U"}, {"id": 14, "box": [122, 364, 138, 391], "bndbox": [[122, 364], [138, 364], [138, 391], [122, 391]], "text": " "}, {"id": 15, "box": [138, 364, 149, 391], "bndbox": [[138, 364], [149, 364], [149, 391], [138, 391]], "text": "S"}, {"id": 16, "box": [149, 364, 162, 391], "bndbox": [[149, 364], [162, 364], [162, 391], [149, 391]], "text": "U"}, {"id": 17, "box": [162, 364, 176, 391], "bndbox": [[162, 364], [176, 364], [176, 391], [162, 391]], "text": "S"}, {"id": 18, "box": [176, 364, 194, 391], "bndbox": [[176, 364], [194, 364], [194, 391], [176, 391]], "text": "U"}]}, {"id": 3, "box": [422, 360, 508, 391], "bndbox": [[422, 362], [507, 360], [508, 389], [423, 391]], "text": "11,000", "words": [{"id": 19, "box": [422, 361, 438, 391], "bndbox": [[422, 362], [437, 361], [438, 390], [423, 391]], "text": "1"}, {"id": 20, "box": [437, 361, 453, 390], "bndbox": [[437, 361], [452, 361], [453, 390], [438, 390]], "text": "1"}, {"id": 21, "box": [452, 361, 465, 390], "bndbox": [[452, 361], [464, 361], [465, 390], [453, 390]], "text": ","}, {"id": 22, "box": [464, 360, 478, 390], "bndbox": [[464, 361], [477, 360], [478, 389], [465, 390]], "text": "0"}, {"id": 23, "box": [477, 360, 493, 389], "bndbox": [[477, 360], [492, 360], [493, 389], [478, 389]], "text": "0"}, {"id": 24, "box": [492, 360, 508, 389], "bndbox": [[492, 360], [507, 360], [508, 389], [493, 389]], "text": "0"}]}, {"id": 4, "box": [64, 398, 194, 425], "bndbox": [[64, 398], [194, 398], [194, 425], [64, 425]], "text": "DISC ITEM", "words": [{"id": 25, "box": [64, 398, 79, 425], "bndbox": [[64, 398], [79, 398], [79, 425], [64, 425]], "text": "D"}, {"id": 26, "box": [79, 398, 95, 425], "bndbox": [[79, 398], [95, 398], [95, 425], [79, 425]], "text": "I"}, {"id": 27, "box": [95, 398, 108, 425], "bndbox": [[95, 398], [108, 398], [108, 425], [95, 425]], "text": "S"}, {"id": 28, "box": [108, 398, 122, 425], "bndbox": [[108, 398], [122, 398], [122, 425], [108, 425]], "text": "C"}, {"id": 29, "box": [122, 398, 137, 425], "bndbox": [[122, 398], [137, 398], [137, 425], [122, 425]], "text": " "}, {"id": 30, "box": [137, 398, 151, 425], "bndbox": [[137, 398], [151, 398], [151, 425], [137, 425]], "text": "I"}, {"id": 31, "box": [151, 398, 167, 425], "bndbox": [[151, 398], [167, 398], [167, 425], [151, 425]], "text": "T"}, {"id": 32, "box": [167, 398, 178, 425], "bndbox": [[167, 398], [178, 398], [178, 425], [167, 425]], "text": "E"}, {"id": 33, "box": [178, 398, 194, 425], "bndbox": [[178, 398], [194, 398], [194, 425], [178, 425]], "text": "M"}]}, {"id": 5, "box": [397, 396, 508, 424], "bndbox": [[397, 396], [508, 396], [508, 424], [397, 424]], "text": "20.000%", "words": [{"id": 34, "box": [397, 396, 424, 424], "bndbox": [[397, 396], [424, 396], [424, 424], [397, 424]], "text": "2"}, {"id": 35, "box": [424, 396, 438, 424], "bndbox": [[424, 396], [438, 396], [438, 424], [424, 424]], "text": "0"}, {"id": 36, "box": [438, 396, 450, 424], "bndbox": [[438, 396], [450, 396], [450, 424], [438, 424]], "text": "."}, {"id": 37, "box": [450, 396, 461, 424], "bndbox": [[450, 396], [461, 396], [461, 424], [450, 424]], "text": "0"}, {"id": 38, "box": [461, 396, 475, 424], "bndbox": [[461, 396], [475, 396], [475, 424], [461, 424]], "text": "0"}, {"id": 39, "box": [475, 396, 489, 424], "bndbox": [[475, 396], [489, 396], [489, 424], [475, 424]], "text": "0"}, {"id": 40, "box": [489, 396, 508, 424], "bndbox": [[489, 396], [508, 396], [508, 424], [489, 424]], "text": "%"}]}, {"id": 6, "box": [64, 431, 152, 459], "bndbox": [[64, 431], [152, 431], [152, 459], [64, 459]], "text": "AMOUNT", "words": [{"id": 41, "box": [64, 431, 77, 459], "bndbox": [[64, 431], [77, 431], [77, 458], [64, 459]], "text": "A"}, {"id": 42, "box": [77, 431, 91, 459], "bndbox": [[77, 431], [91, 431], [91, 459], [77, 458]], "text": "M"}, {"id": 43, "box": [91, 431, 105, 459], "bndbox": [[91, 431], [105, 431], [105, 459], [91, 459]], "text": "O"}, {"id": 44, "box": [105, 431, 119, 459], "bndbox": [[105, 431], [119, 431], [119, 459], [105, 459]], "text": "U"}, {"id": 45, "box": [119, 431, 135, 459], "bndbox": [[119, 431], [135, 431], [135, 459], [119, 459]], "text": "N"}, {"id": 46, "box": [135, 431, 152, 459], "bndbox": [[135, 431], [152, 431], [152, 459], [135, 459]], "text": "T"}]}, {"id": 7, "box": [424, 429, 509, 457], "bndbox": [[424, 429], [509, 429], [509, 457], [424, 457]], "text": "-2,200", "words": [{"id": 47, "box": [424, 429, 438, 457], "bndbox": [[424, 429], [438, 429], [438, 457], [424, 457]], "text": "-"}, {"id": 48, "box": [438, 429, 452, 457], "bndbox": [[438, 429], [452, 429], [452, 457], [438, 457]], "text": "2"}, {"id": 49, "box": [452, 429, 466, 457], "bndbox": [[452, 429], [466, 429], [466, 457], [452, 457]], "text": ","}, {"id": 50, "box": [466, 429, 480, 457], "bndbox": [[466, 429], [480, 429], [480, 457], [466, 457]], "text": "2"}, {"id": 51, "box": [480, 429, 494, 457], "bndbox": [[480, 429], [494, 429], [494, 457], [480, 457]], "text": "0"}, {"id": 52, "box": [494, 429, 509, 457], "bndbox": [[494, 429], [509, 429], [509, 457], [494, 457]], "text": "0"}]}, {"id": 8, "box": [63, 463, 221, 493], "bndbox": [[63, 466], [221, 463], [221, 490], [63, 493]], "text": "PISANG KEJU", "words": [{"id": 53, "box": [63, 465, 78, 493], "bndbox": [[63, 466], [78, 465], [78, 492], [63, 493]], "text": "P"}, {"id": 54, "box": [78, 465, 94, 492], "bndbox": [[78, 465], [94, 465], [94, 492], [78, 492]], "text": "I"}, {"id": 55, "box": [94, 465, 108, 492], "bndbox": [[94, 465], [108, 465], [108, 492], [94, 492]], "text": "S"}, {"id": 56, "box": [108, 464, 121, 492], "bndbox": [[108, 465], [121, 464], [121, 491], [108, 492]], "text": "A"}, {"id": 57, "box": [121, 464, 135, 491], "bndbox": [[121, 464], [135, 464], [135, 491], [121, 491]], "text": "N"}, {"id": 58, "box": [135, 464, 146, 491], "bndbox": [[135, 464], [146, 464], [146, 491], [135, 491]], "text": "G"}, {"id": 59, "box": [146, 464, 162, 491], "bndbox": [[146, 464], [162, 464], [162, 491], [146, 491]], "text": " "}, {"id": 60, "box": [162, 463, 178, 491], "bndbox": [[162, 464], [178, 463], [178, 490], [162, 491]], "text": "K"}, {"id": 61, "box": [178, 463, 193, 490], "bndbox": [[178, 463], [193, 463], [193, 490], [178, 490]], "text": "E"}, {"id": 62, "box": [193, 463, 205, 490], "bndbox": [[193, 463], [205, 463], [205, 490], [193, 490]], "text": "J"}, {"id": 63, "box": [205, 463, 221, 490], "bndbox": [[205, 463], [221, 463], [221, 490], [205, 490]], "text": "U"}]}, {"id": 9, "box": [425, 463, 510, 491], "bndbox": [[425, 463], [510, 463], [510, 491], [425, 491]], "text": "11,500", "words": [{"id": 64, "box": [425, 463, 439, 491], "bndbox": [[425, 463], [439, 463], [439, 491], [425, 491]], "text": "1"}, {"id": 65, "box": [439, 463, 453, 491], "bndbox": [[439, 463], [453, 463], [453, 491], [439, 491]], "text": "1"}, {"id": 66, "box": [453, 463, 467, 491], "bndbox": [[453, 463], [467, 463], [467, 491], [453, 491]], "text": ","}, {"id": 67, "box": [467, 463, 481, 491], "bndbox": [[467, 463], [481, 463], [481, 491], [467, 491]], "text": "5"}, {"id": 68, "box": [481, 463, 495, 491], "bndbox": [[481, 463], [495, 463], [495, 491], [481, 491]], "text": "0"}, {"id": 69, "box": [495, 463, 510, 491], "bndbox": [[495, 463], [510, 463], [510, 491], [495, 491]], "text": "0"}]}, {"id": 10, "box": [61, 497, 193, 528], "bndbox": [[61, 500], [192, 497], [193, 525], [62, 528]], "text": "DISC ITEM", "words": [{"id": 70, "box": [61, 499, 78, 528], "bndbox": [[61, 500], [77, 499], [78, 527], [62, 528]], "text": "D"}, {"id": 71, "box": [77, 499, 94, 527], "bndbox": [[77, 499], [93, 499], [94, 527], [78, 527]], "text": "I"}, {"id": 72, "box": [93, 498, 108, 527], "bndbox": [[93, 499], [107, 498], [108, 526], [94, 527]], "text": "S"}, {"id": 73, "box": [107, 498, 120, 526], "bndbox": [[107, 498], [119, 498], [120, 526], [108, 526]], "text": "C"}, {"id": 74, "box": [119, 498, 136, 526], "bndbox": [[119, 498], [135, 498], [136, 526], [120, 526]], "text": " "}, {"id": 75, "box": [135, 497, 150, 526], "bndbox": [[135, 498], [149, 497], [150, 525], [136, 526]], "text": "I"}, {"id": 76, "box": [149, 497, 164, 525], "bndbox": [[149, 497], [163, 497], [164, 525], [150, 525]], "text": "T"}, {"id": 77, "box": [163, 497, 178, 525], "bndbox": [[163, 497], [177, 497], [178, 525], [164, 525]], "text": "E"}, {"id": 78, "box": [177, 497, 193, 525], "bndbox": [[177, 497], [192, 497], [193, 525], [178, 525]], "text": "M"}]}, {"id": 11, "box": [399, 496, 511, 524], "bndbox": [[399, 496], [511, 496], [511, 524], [399, 524]], "text": "20.000%", "words": [{"id": 79, "box": [399, 496, 427, 524], "bndbox": [[399, 496], [427, 496], [427, 524], [399, 524]], "text": "2"}, {"id": 80, "box": [427, 496, 441, 524], "bndbox": [[427, 496], [441, 496], [441, 524], [427, 524]], "text": "0"}, {"id": 81, "box": [441, 496, 455, 524], "bndbox": [[441, 496], [455, 496], [455, 524], [441, 524]], "text": "."}, {"id": 82, "box": [455, 496, 469, 524], "bndbox": [[455, 496], [469, 496], [469, 524], [455, 524]], "text": "0"}, {"id": 83, "box": [469, 496, 483, 524], "bndbox": [[469, 496], [483, 496], [483, 524], [469, 524]], "text": "0"}, {"id": 84, "box": [483, 496, 494, 524], "bndbox": [[483, 496], [494, 496], [494, 524], [483, 524]], "text": "0"}, {"id": 85, "box": [494, 496, 511, 524], "bndbox": [[494, 496], [511, 496], [511, 524], [494, 524]], "text": "%"}]}, {"id": 12, "box": [60, 532, 150, 564], "bndbox": [[60, 535], [149, 532], [150, 561], [61, 564]], "text": "AMOUNT", "words": [{"id": 86, "box": [60, 534, 75, 564], "bndbox": [[60, 535], [74, 534], [75, 563], [61, 564]], "text": "A"}, {"id": 87, "box": [74, 534, 90, 563], "bndbox": [[74, 534], [89, 534], [90, 563], [75, 563]], "text": "M"}, {"id": 88, "box": [89, 533, 105, 563], "bndbox": [[89, 534], [104, 533], [105, 562], [90, 563]], "text": "O"}, {"id": 89, "box": [104, 533, 120, 562], "bndbox": [[104, 533], [119, 533], [120, 562], [105, 562]], "text": "U"}, {"id": 90, "box": [119, 532, 135, 562], "bndbox": [[119, 533], [134, 532], [135, 561], [120, 562]], "text": "N"}, {"id": 91, "box": [134, 532, 150, 561], "bndbox": [[134, 532], [149, 532], [150, 561], [135, 561]], "text": "T"}]}, {"id": 13, "box": [427, 530, 512, 559], "bndbox": [[427, 530], [512, 530], [512, 559], [427, 559]], "text": "2,300", "words": [{"id": 92, "box": [427, 530, 457, 559], "bndbox": [[427, 530], [457, 530], [457, 559], [427, 559]], "text": "2"}, {"id": 93, "box": [457, 530, 472, 559], "bndbox": [[457, 530], [472, 530], [472, 559], [457, 559]], "text": ","}, {"id": 94, "box": [472, 530, 484, 559], "bndbox": [[472, 530], [484, 530], [484, 559], [472, 559]], "text": "3"}, {"id": 95, "box": [484, 530, 497, 559], "bndbox": [[484, 530], [497, 530], [497, 559], [484, 559]], "text": "0"}, {"id": 96, "box": [497, 530, 512, 559], "bndbox": [[497, 530], [512, 530], [512, 559], [497, 559]], "text": "0"}]}, {"id": 14, "box": [60, 566, 243, 597], "bndbox": [[60, 570], [243, 566], [243, 593], [60, 597]], "text": "PLASTIK KECIL", "words": [{"id": 97, "box": [60, 569, 73, 597], "bndbox": [[60, 570], [73, 569], [73, 596], [60, 597]], "text": "P"}, {"id": 98, "box": [73, 569, 89, 596], "bndbox": [[73, 569], [89, 569], [89, 596], [73, 596]], "text": "L"}, {"id": 99, "box": [89, 569, 104, 596], "bndbox": [[89, 569], [104, 569], [104, 596], [89, 596]], "text": "A"}, {"id": 100, "box": [104, 568, 120, 596], "bndbox": [[104, 569], [120, 568], [120, 595], [104, 596]], "text": "S"}, {"id": 101, "box": [120, 568, 135, 595], "bndbox": [[120, 568], [135, 568], [135, 595], [120, 595]], "text": "T"}, {"id": 102, "box": [135, 568, 147, 595], "bndbox": [[135, 568], [147, 568], [147, 595], [135, 595]], "text": "I"}, {"id": 103, "box": [147, 567, 158, 595], "bndbox": [[147, 568], [158, 567], [158, 594], [147, 595]], "text": "K"}, {"id": 104, "box": [158, 567, 176, 594], "bndbox": [[158, 567], [176, 567], [176, 594], [158, 594]], "text": " "}, {"id": 105, "box": [176, 567, 189, 594], "bndbox": [[176, 567], [189, 567], [189, 594], [176, 594]], "text": "K"}, {"id": 106, "box": [189, 566, 202, 594], "bndbox": [[189, 567], [202, 566], [202, 593], [189, 594]], "text": "E"}, {"id": 107, "box": [202, 566, 216, 593], "bndbox": [[202, 566], [216, 566], [216, 593], [202, 593]], "text": "C"}, {"id": 108, "box": [216, 566, 229, 593], "bndbox": [[216, 566], [229, 566], [229, 593], [216, 593]], "text": "I"}, {"id": 109, "box": [229, 566, 243, 593], "bndbox": [[229, 566], [243, 566], [243, 593], [229, 593]], "text": "L"}]}, {"id": 15, "box": [494, 566, 514, 593], "bndbox": [[494, 566], [514, 566], [514, 593], [494, 593]], "text": "0", "words": [{"id": 110, "box": [494, 566, 514, 593], "bndbox": [[494, 566], [514, 566], [514, 593], [494, 593]], "text": "0"}]}, {"id": 16, "box": [59, 601, 175, 633], "bndbox": [[59, 604], [174, 601], [175, 630], [60, 633]], "text": "SUBTOTAL", "words": [{"id": 111, "box": [59, 603, 74, 633], "bndbox": [[59, 604], [73, 603], [74, 632], [60, 633]], "text": "S"}, {"id": 112, "box": [73, 603, 88, 632], "bndbox": [[73, 603], [87, 603], [88, 632], [74, 632]], "text": "U"}, {"id": 113, "box": [87, 602, 103, 632], "bndbox": [[87, 603], [102, 602], [103, 631], [88, 632]], "text": "B"}, {"id": 114, "box": [102, 602, 117, 631], "bndbox": [[102, 602], [116, 602], [117, 631], [103, 631]], "text": "T"}, {"id": 115, "box": [116, 602, 131, 631], "bndbox": [[116, 602], [130, 602], [131, 631], [117, 631]], "text": "O"}, {"id": 116, "box": [130, 601, 146, 631], "bndbox": [[130, 602], [145, 601], [146, 630], [131, 631]], "text": "T"}, {"id": 117, "box": [145, 601, 160, 630], "bndbox": [[145, 601], [159, 601], [160, 630], [146, 630]], "text": "A"}, {"id": 118, "box": [159, 601, 175, 630], "bndbox": [[159, 601], [174, 601], [175, 630], [160, 630]], "text": "L"}]}, {"id": 17, "box": [430, 600, 514, 629], "bndbox": [[430, 600], [514, 600], [514, 629], [430, 629]], "text": "18,000", "words": [{"id": 119, "box": [430, 600, 444, 629], "bndbox": [[430, 600], [444, 600], [444, 629], [430, 629]], "text": "1"}, {"id": 120, "box": [444, 600, 459, 629], "bndbox": [[444, 600], [459, 600], [459, 629], [444, 629]], "text": "8"}, {"id": 121, "box": [459, 600, 472, 629], "bndbox": [[459, 600], [472, 600], [472, 629], [459, 629]], "text": ","}, {"id": 122, "box": [472, 600, 484, 629], "bndbox": [[472, 600], [484, 600], [484, 629], [472, 629]], "text": "0"}, {"id": 123, "box": [484, 600, 499, 629], "bndbox": [[484, 600], [499, 600], [499, 629], [484, 629]], "text": "0"}, {"id": 124, "box": [499, 600, 514, 629], "bndbox": [[499, 600], [514, 600], [514, 629], [499, 629]], "text": "0"}]}, {"id": 18, "box": [62, 635, 201, 670], "bndbox": [[62, 639], [200, 635], [201, 666], [63, 670]], "text": "TOTAL", "words": [{"id": 125, "box": [62, 638, 88, 670], "bndbox": [[62, 639], [87, 638], [88, 669], [63, 670]], "text": "T"}, {"id": 126, "box": [87, 637, 116, 669], "bndbox": [[87, 638], [115, 637], [116, 668], [88, 669]], "text": "O"}, {"id": 127, "box": [115, 636, 144, 668], "bndbox": [[115, 637], [143, 636], [144, 667], [116, 668]], "text": "T"}, {"id": 128, "box": [143, 635, 172, 667], "bndbox": [[143, 636], [171, 635], [172, 666], [144, 667]], "text": "A"}, {"id": 129, "box": [171, 635, 201, 666], "bndbox": [[171, 635], [200, 635], [201, 666], [172, 666]], "text": "L"}]}, {"id": 19, "box": [429, 632, 515, 666], "bndbox": [[429, 634], [514, 632], [515, 664], [430, 666]], "text": "18,000", "words": [{"id": 130, "box": [429, 633, 443, 666], "bndbox": [[429, 634], [442, 633], [443, 665], [430, 666]], "text": "1"}, {"id": 131, "box": [442, 633, 456, 665], "bndbox": [[442, 633], [455, 633], [456, 665], [443, 665]], "text": "8"}, {"id": 132, "box": [455, 633, 472, 665], "bndbox": [[455, 633], [471, 633], [472, 665], [456, 665]], "text": ","}, {"id": 133, "box": [471, 632, 485, 665], "bndbox": [[471, 633], [484, 632], [485, 664], [472, 665]], "text": "0"}, {"id": 134, "box": [484, 632, 499, 664], "bndbox": [[484, 632], [498, 632], [499, 664], [485, 664]], "text": "0"}, {"id": 135, "box": [498, 632, 515, 664], "bndbox": [[498, 632], [514, 632], [515, 664], [499, 664]], "text": "0"}]}, {"id": 20, "box": [57, 672, 177, 706], "bndbox": [[57, 675], [176, 672], [177, 703], [58, 706]], "text": "CASH", "words": [{"id": 136, "box": [57, 674, 89, 706], "bndbox": [[57, 675], [88, 674], [89, 705], [58, 706]], "text": "C"}, {"id": 137, "box": [88, 673, 117, 705], "bndbox": [[88, 674], [116, 673], [117, 704], [89, 705]], "text": "A"}, {"id": 138, "box": [116, 672, 145, 704], "bndbox": [[116, 673], [144, 672], [145, 703], [117, 704]], "text": "S"}, {"id": 139, "box": [144, 672, 177, 703], "bndbox": [[144, 672], [176, 672], [177, 703], [145, 703]], "text": "H"}]}, {"id": 21, "box": [429, 668, 515, 700], "bndbox": [[429, 670], [514, 668], [515, 698], [430, 700]], "text": "20,000", "words": [{"id": 140, "box": [429, 669, 445, 700], "bndbox": [[429, 670], [444, 669], [445, 699], [430, 700]], "text": "2"}, {"id": 141, "box": [444, 669, 460, 699], "bndbox": [[444, 669], [459, 669], [460, 699], [445, 699]], "text": "0"}, {"id": 142, "box": [459, 668, 475, 699], "bndbox": [[459, 669], [474, 668], [475, 698], [460, 699]], "text": ","}, {"id": 143, "box": [474, 668, 487, 698], "bndbox": [[474, 668], [486, 668], [487, 698], [475, 698]], "text": "0"}, {"id": 144, "box": [486, 668, 500, 698], "bndbox": [[486, 668], [499, 668], [500, 698], [487, 698]], "text": "0"}, {"id": 145, "box": [499, 668, 515, 698], "bndbox": [[499, 668], [514, 668], [515, 698], [500, 698]], "text": "0"}]}, {"id": 22, "box": [58, 708, 228, 740], "bndbox": [[58, 712], [227, 708], [228, 736], [59, 740]], "text": "CHANGE", "words": [{"id": 146, "box": [58, 711, 89, 740], "bndbox": [[58, 712], [88, 711], [89, 739], [59, 740]], "text": "C"}, {"id": 147, "box": [88, 710, 117, 739], "bndbox": [[88, 711], [116, 710], [117, 738], [89, 739]], "text": "H"}, {"id": 148, "box": [116, 709, 145, 738], "bndbox": [[116, 710], [144, 709], [145, 737], [117, 738]], "text": "A"}, {"id": 149, "box": [144, 709, 174, 737], "bndbox": [[144, 709], [173, 709], [174, 737], [145, 737]], "text": "N"}, {"id": 150, "box": [173, 708, 204, 737], "bndbox": [[173, 709], [203, 708], [204, 736], [174, 737]], "text": "G"}, {"id": 151, "box": [203, 708, 228, 736], "bndbox": [[203, 708], [227, 708], [228, 736], [204, 736]], "text": "E"}]}, {"id": 23, "box": [440, 701, 518, 736], "bndbox": [[440, 705], [516, 701], [518, 733], [442, 736]], "text": "2,000", "words": [{"id": 152, "box": [440, 704, 461, 736], "bndbox": [[440, 705], [459, 704], [461, 735], [442, 736]], "text": "2"}, {"id": 153, "box": [459, 703, 474, 735], "bndbox": [[459, 704], [472, 703], [474, 734], [461, 735]], "text": ","}, {"id": 154, "box": [472, 702, 490, 734], "bndbox": [[472, 703], [488, 702], [490, 734], [474, 734]], "text": "0"}, {"id": 155, "box": [488, 701, 504, 734], "bndbox": [[488, 702], [502, 701], [504, 733], [490, 734]], "text": "0"}, {"id": 156, "box": [502, 701, 518, 733], "bndbox": [[502, 701], [516, 701], [518, 733], [504, 733]], "text": "0"}]}], "uid": "train_0664", "label_entities": [{"entity_id": 0, "label": "menu.nm", "word_idx": [10, 11, 12, 13, 14, 15, 16, 17, 18]}, {"entity_id": 1, "label": "menu.price", "word_idx": [19, 20, 21, 22, 23, 24]}, {"entity_id": 2, "label": "menu.discountprice", "word_idx": [25, 26, 27, 28, 29, 30, 31, 32, 33, 34, 35, 36, 37, 38, 39, 40, 41, 42, 43, 44, 45, 46, 47, 48, 49, 50, 51, 52]}, {"entity_id": 3, "label": "menu.nm", "word_idx": [53, 54, 55, 56, 57, 58, 59, 60, 61, 62, 63]}, {"entity_id": 4, "label": "menu.price", "word_idx": [64, 65, 66, 67, 68, 69]}, {"entity_id": 5, "label": "menu.discountprice", "word_idx": [70, 71, 72, 73, 74, 75, 76, 77, 78, 79, 80, 81, 82, 83, 84, 85, 86, 87, 88, 89, 90, 91, 92, 93, 94, 95, 96]}, {"entity_id": 6, "label": "menu.nm", "word_idx": [97, 98, 99, 100, 101, 102, 103, 104, 105, 106, 107, 108, 109]}, {"entity_id": 7, "label": "menu.price", "word_idx": [110]}, {"entity_id": 8, "label": "sub_total.subtotal_price", "word_idx": [111, 112, 113, 114, 115, 116, 117, 118, 119, 120, 121, 122, 123, 124]}, {"entity_id": 9, "label": "total.total_price", "word_idx": [125, 126, 127, 128, 129, 130, 131, 132, 133, 134, 135]}, {"entity_id": 10, "label": "total.cashprice", "word_idx": [136, 137, 138, 139, 140, 141, 142, 143, 144, 145]}, {"entity_id": 11, "label": "total.changeprice", "word_idx": [146, 147, 148, 149, 150, 151, 152, 153, 154, 155, 156]}]}