{"img": {"height": 1000, "width": 782, "image_path": "92327794.png"}, "document": [{"id": 0, "box": [224, 12, 476, 28], "bndbox": [[224, 14], [476, 12], [476, 27], [224, 28]], "text": "2:42PM LORILRD TOBACCO 919 373 6917", "words": [{"id": 0, "box": [224, 13, 241, 28], "bndbox": [[224, 14], [241, 13], [241, 27], [224, 28]], "text": "2"}, {"id": 1, "box": [241, 13, 248, 27], "bndbox": [[241, 13], [248, 13], [248, 27], [241, 27]], "text": ":"}, {"id": 2, "box": [248, 13, 256, 27], "bndbox": [[248, 13], [256, 13], [256, 27], [248, 27]], "text": "4"}, {"id": 3, "box": [256, 13, 262, 27], "bndbox": [[256, 13], [262, 13], [262, 27], [256, 27]], "text": "2"}, {"id": 4, "box": [262, 13, 268, 27], "bndbox": [[262, 13], [268, 13], [268, 27], [262, 27]], "text": "P"}, {"id": 5, "box": [268, 13, 275, 27], "bndbox": [[268, 13], [275, 13], [275, 27], [268, 27]], "text": "M"}, {"id": 6, "box": [275, 13, 282, 27], "bndbox": [[275, 13], [282, 13], [282, 27], [275, 27]], "text": " "}, {"id": 7, "box": [282, 13, 288, 27], "bndbox": [[282, 13], [288, 13], [288, 27], [282, 27]], "text": "L"}, {"id": 8, "box": [288, 13, 296, 27], "bndbox": [[288, 13], [296, 13], [296, 27], [288, 27]], "text": "O"}, {"id": 9, "box": [296, 13, 303, 27], "bndbox": [[296, 13], [303, 13], [303, 27], [296, 27]], "text": "R"}, {"id": 10, "box": [303, 13, 310, 27], "bndbox": [[303, 13], [310, 13], [310, 27], [303, 27]], "text": "I"}, {"id": 11, "box": [310, 13, 322, 27], "bndbox": [[310, 13], [322, 13], [322, 27], [310, 27]], "text": "L"}, {"id": 12, "box": [322, 13, 336, 27], "bndbox": [[322, 13], [336, 13], [336, 27], [322, 27]], "text": "R"}, {"id": 13, "box": [336, 13, 342, 27], "bndbox": [[336, 13], [342, 13], [342, 27], [336, 27]], "text": "D"}, {"id": 14, "box": [342, 13, 350, 27], "bndbox": [[342, 13], [350, 13], [350, 27], [342, 27]], "text": " "}, {"id": 15, "box": [350, 12, 356, 27], "bndbox": [[350, 13], [356, 12], [356, 27], [350, 27]], "text": "T"}, {"id": 16, "box": [356, 12, 362, 27], "bndbox": [[356, 12], [362, 12], [362, 27], [356, 27]], "text": "O"}, {"id": 17, "box": [362, 12, 368, 27], "bndbox": [[362, 12], [368, 12], [368, 27], [362, 27]], "text": "B"}, {"id": 18, "box": [368, 12, 374, 27], "bndbox": [[368, 12], [374, 12], [374, 27], [368, 27]], "text": "A"}, {"id": 19, "box": [374, 12, 381, 27], "bndbox": [[374, 12], [381, 12], [381, 27], [374, 27]], "text": "C"}, {"id": 20, "box": [381, 12, 388, 27], "bndbox": [[381, 12], [388, 12], [388, 27], [381, 27]], "text": "C"}, {"id": 21, "box": [388, 12, 394, 27], "bndbox": [[388, 12], [394, 12], [394, 27], [388, 27]], "text": "O"}, {"id": 22, "box": [394, 12, 401, 27], "bndbox": [[394, 12], [401, 12], [401, 27], [394, 27]], "text": " "}, {"id": 23, "box": [401, 12, 407, 27], "bndbox": [[401, 12], [407, 12], [407, 27], [401, 27]], "text": "9"}, {"id": 24, "box": [407, 12, 413, 27], "bndbox": [[407, 12], [413, 12], [413, 27], [407, 27]], "text": "1"}, {"id": 25, "box": [413, 12, 419, 27], "bndbox": [[413, 12], [419, 12], [419, 27], [413, 27]], "text": "9"}, {"id": 26, "box": [419, 12, 426, 27], "bndbox": [[419, 12], [426, 12], [426, 27], [419, 27]], "text": " "}, {"id": 27, "box": [426, 12, 432, 27], "bndbox": [[426, 12], [432, 12], [432, 27], [426, 27]], "text": "3"}, {"id": 28, "box": [432, 12, 438, 27], "bndbox": [[432, 12], [438, 12], [438, 27], [432, 27]], "text": "7"}, {"id": 29, "box": [438, 12, 444, 27], "bndbox": [[438, 12], [444, 12], [444, 27], [438, 27]], "text": "3"}, {"id": 30, "box": [444, 12, 451, 27], "bndbox": [[444, 12], [451, 12], [451, 27], [444, 27]], "text": " "}, {"id": 31, "box": [451, 12, 457, 27], "bndbox": [[451, 12], [457, 12], [457, 27], [451, 27]], "text": "6"}, {"id": 32, "box": [457, 12, 463, 27], "bndbox": [[457, 12], [463, 12], [463, 27], [457, 27]], "text": "9"}, {"id": 33, "box": [463, 12, 469, 27], "bndbox": [[463, 12], [469, 12], [469, 27], [463, 27]], "text": "1"}, {"id": 34, "box": [469, 12, 476, 27], "bndbox": [[469, 12], [476, 12], [476, 27], [469, 27]], "text": "7"}]}, {"id": 1, "box": [149, 17, 189, 27], "bndbox": [[149, 17], [189, 17], [189, 27], [149, 27]], "text": "JUL22", "words": [{"id": 35, "box": [149, 17, 155, 27], "bndbox": [[149, 17], [155, 17], [155, 27], [149, 27]], "text": "J"}, {"id": 36, "box": [155, 17, 161, 27], "bndbox": [[155, 17], [161, 17], [161, 27], [155, 27]], "text": "U"}, {"id": 37, "box": [161, 17, 171, 27], "bndbox": [[161, 17], [171, 17], [171, 27], [161, 27]], "text": "L"}, {"id": 38, "box": [171, 17, 181, 27], "bndbox": [[171, 17], [181, 17], [181, 27], [171, 27]], "text": "2"}, {"id": 39, "box": [181, 17, 189, 27], "bndbox": [[181, 17], [189, 17], [189, 27], [181, 27]], "text": "2"}]}, {"id": 2, "box": [664, 11, 702, 26], "bndbox": [[664, 11], [702, 11], [702, 26], [664, 26]], "text": "P.1/8", "words": [{"id": 40, "box": [664, 11, 672, 26], "bndbox": [[664, 11], [672, 11], [672, 25], [664, 26]], "text": "P"}, {"id": 41, "box": [672, 11, 679, 26], "bndbox": [[672, 11], [679, 11], [679, 26], [672, 25]], "text": "."}, {"id": 42, "box": [679, 11, 686, 26], "bndbox": [[679, 11], [686, 11], [686, 26], [679, 26]], "text": "1"}, {"id": 43, "box": [686, 11, 693, 26], "bndbox": [[686, 11], [693, 11], [693, 26], [686, 26]], "text": "/"}, {"id": 44, "box": [693, 11, 702, 26], "bndbox": [[693, 11], [702, 11], [702, 26], [693, 26]], "text": "8"}]}, {"id": 3, "box": [177, 117, 645, 136], "bndbox": [[178, 117], [645, 120], [645, 136], [177, 133]], "text": "TOBACCO COMPANY2525 E Market Stroet P.O.Box 21683Greonsboro,North Carolina 27420-1688", "words": [{"id": 45, "box": [177, 117, 191, 133], "bndbox": [[178, 117], [191, 117], [190, 133], [177, 133]], "text": "T"}, {"id": 46, "box": [190, 117, 199, 133], "bndbox": [[191, 117], [199, 117], [198, 133], [190, 133]], "text": "O"}, {"id": 47, "box": [198, 117, 207, 133], "bndbox": [[199, 117], [207, 117], [206, 133], [198, 133]], "text": "B"}, {"id": 48, "box": [206, 117, 215, 133], "bndbox": [[207, 117], [215, 117], [214, 133], [206, 133]], "text": "A"}, {"id": 49, "box": [214, 117, 223, 133], "bndbox": [[215, 117], [223, 117], [222, 133], [214, 133]], "text": "C"}, {"id": 50, "box": [222, 117, 231, 133], "bndbox": [[223, 117], [231, 117], [230, 133], [222, 133]], "text": "C"}, {"id": 51, "box": [230, 117, 238, 133], "bndbox": [[231, 117], [238, 117], [237, 133], [230, 133]], "text": "O"}, {"id": 52, "box": [237, 117, 243, 133], "bndbox": [[238, 117], [243, 117], [242, 133], [237, 133]], "text": " "}, {"id": 53, "box": [242, 117, 250, 133], "bndbox": [[243, 117], [250, 117], [249, 133], [242, 133]], "text": "C"}, {"id": 54, "box": [249, 117, 258, 133], "bndbox": [[250, 117], [258, 117], [257, 133], [249, 133]], "text": "O"}, {"id": 55, "box": [257, 117, 267, 133], "bndbox": [[258, 117], [267, 117], [266, 133], [257, 133]], "text": "M"}, {"id": 56, "box": [266, 117, 276, 133], "bndbox": [[267, 117], [276, 117], [275, 133], [266, 133]], "text": "P"}, {"id": 57, "box": [275, 117, 283, 133], "bndbox": [[276, 117], [283, 117], [282, 133], [275, 133]], "text": "A"}, {"id": 58, "box": [282, 117, 290, 133], "bndbox": [[283, 117], [290, 117], [289, 133], [282, 133]], "text": "N"}, {"id": 59, "box": [289, 117, 303, 133], "bndbox": [[290, 117], [303, 117], [302, 133], [289, 133]], "text": "Y"}, {"id": 60, "box": [302, 117, 315, 133], "bndbox": [[303, 117], [315, 117], [314, 133], [302, 133]], "text": "2"}, {"id": 61, "box": [314, 117, 320, 133], "bndbox": [[315, 117], [320, 117], [320, 133], [314, 133]], "text": "5"}, {"id": 62, "box": [320, 117, 324, 133], "bndbox": [[320, 117], [324, 117], [324, 133], [320, 133]], "text": "2"}, {"id": 63, "box": [324, 117, 330, 133], "bndbox": [[324, 117], [330, 117], [329, 133], [324, 133]], "text": "5"}, {"id": 64, "box": [329, 117, 334, 134], "bndbox": [[330, 117], [334, 118], [333, 134], [329, 133]], "text": " "}, {"id": 65, "box": [333, 118, 339, 134], "bndbox": [[334, 118], [339, 118], [338, 134], [333, 134]], "text": "E"}, {"id": 66, "box": [338, 118, 344, 134], "bndbox": [[339, 118], [344, 118], [344, 134], [338, 134]], "text": " "}, {"id": 67, "box": [344, 118, 351, 134], "bndbox": [[344, 118], [351, 118], [350, 134], [344, 134]], "text": "M"}, {"id": 68, "box": [350, 118, 356, 134], "bndbox": [[351, 118], [356, 118], [356, 134], [350, 134]], "text": "a"}, {"id": 69, "box": [356, 118, 360, 134], "bndbox": [[356, 118], [360, 118], [360, 134], [356, 134]], "text": "r"}, {"id": 70, "box": [360, 118, 364, 134], "bndbox": [[360, 118], [364, 118], [364, 134], [360, 134]], "text": "k"}, {"id": 71, "box": [364, 118, 370, 134], "bndbox": [[364, 118], [370, 118], [369, 134], [364, 134]], "text": "e"}, {"id": 72, "box": [369, 118, 372, 134], "bndbox": [[370, 118], [372, 118], [372, 134], [369, 134]], "text": "t"}, {"id": 73, "box": [372, 118, 378, 134], "bndbox": [[372, 118], [378, 118], [377, 134], [372, 134]], "text": " "}, {"id": 74, "box": [377, 118, 380, 134], "bndbox": [[378, 118], [380, 118], [380, 134], [377, 134]], "text": "S"}, {"id": 75, "box": [380, 118, 386, 134], "bndbox": [[380, 118], [386, 118], [385, 134], [380, 134]], "text": "t"}, {"id": 76, "box": [385, 118, 388, 134], "bndbox": [[386, 118], [388, 118], [388, 134], [385, 134]], "text": "r"}, {"id": 77, "box": [388, 118, 392, 134], "bndbox": [[388, 118], [392, 118], [392, 134], [388, 134]], "text": "o"}, {"id": 78, "box": [392, 118, 396, 134], "bndbox": [[392, 118], [396, 118], [396, 134], [392, 134]], "text": "e"}, {"id": 79, "box": [396, 118, 402, 134], "bndbox": [[396, 118], [402, 118], [401, 134], [396, 134]], "text": "t"}, {"id": 80, "box": [401, 118, 406, 134], "bndbox": [[402, 118], [406, 118], [405, 134], [401, 134]], "text": " "}, {"id": 81, "box": [405, 118, 411, 134], "bndbox": [[406, 118], [411, 118], [411, 134], [405, 134]], "text": "P"}, {"id": 82, "box": [411, 118, 416, 134], "bndbox": [[411, 118], [416, 118], [416, 134], [411, 134]], "text": "."}, {"id": 83, "box": [416, 118, 420, 134], "bndbox": [[416, 118], [420, 118], [420, 134], [416, 134]], "text": "O"}, {"id": 84, "box": [420, 118, 427, 134], "bndbox": [[420, 118], [427, 118], [427, 134], [420, 134]], "text": "."}, {"id": 85, "box": [427, 118, 432, 134], "bndbox": [[427, 118], [432, 118], [432, 134], [427, 134]], "text": "B"}, {"id": 86, "box": [432, 118, 438, 134], "bndbox": [[432, 118], [438, 118], [437, 134], [432, 134]], "text": "o"}, {"id": 87, "box": [437, 118, 443, 134], "bndbox": [[438, 118], [443, 118], [443, 134], [437, 134]], "text": "x"}, {"id": 88, "box": [443, 118, 447, 134], "bndbox": [[443, 118], [447, 118], [447, 134], [443, 134]], "text": " "}, {"id": 89, "box": [447, 118, 451, 134], "bndbox": [[447, 118], [451, 118], [451, 134], [447, 134]], "text": "2"}, {"id": 90, "box": [451, 118, 456, 134], "bndbox": [[451, 118], [456, 118], [456, 134], [451, 134]], "text": "1"}, {"id": 91, "box": [456, 118, 462, 134], "bndbox": [[456, 118], [462, 118], [461, 134], [456, 134]], "text": "6"}, {"id": 92, "box": [461, 118, 467, 134], "bndbox": [[462, 118], [467, 118], [467, 134], [461, 134]], "text": "8"}, {"id": 93, "box": [467, 118, 475, 134], "bndbox": [[467, 118], [475, 118], [475, 134], [467, 134]], "text": "3"}, {"id": 94, "box": [475, 118, 483, 134], "bndbox": [[475, 118], [483, 118], [483, 134], [475, 134]], "text": "G"}, {"id": 95, "box": [483, 118, 488, 134], "bndbox": [[483, 118], [488, 118], [488, 134], [483, 134]], "text": "r"}, {"id": 96, "box": [488, 118, 494, 135], "bndbox": [[488, 118], [494, 119], [493, 135], [488, 134]], "text": "e"}, {"id": 97, "box": [493, 119, 498, 135], "bndbox": [[494, 119], [498, 119], [497, 135], [493, 135]], "text": "o"}, {"id": 98, "box": [497, 119, 502, 135], "bndbox": [[498, 119], [502, 119], [501, 135], [497, 135]], "text": "n"}, {"id": 99, "box": [501, 119, 507, 135], "bndbox": [[502, 119], [507, 119], [507, 135], [501, 135]], "text": "s"}, {"id": 100, "box": [507, 119, 512, 135], "bndbox": [[507, 119], [512, 119], [512, 135], [507, 135]], "text": "b"}, {"id": 101, "box": [512, 119, 518, 135], "bndbox": [[512, 119], [518, 119], [517, 135], [512, 135]], "text": "o"}, {"id": 102, "box": [517, 119, 522, 135], "bndbox": [[518, 119], [522, 119], [521, 135], [517, 135]], "text": "r"}, {"id": 103, "box": [521, 119, 526, 135], "bndbox": [[522, 119], [526, 119], [525, 135], [521, 135]], "text": "o"}, {"id": 104, "box": [525, 119, 532, 135], "bndbox": [[526, 119], [532, 119], [532, 135], [525, 135]], "text": ","}, {"id": 105, "box": [532, 119, 539, 135], "bndbox": [[532, 119], [539, 119], [539, 135], [532, 135]], "text": "N"}, {"id": 106, "box": [539, 119, 543, 135], "bndbox": [[539, 119], [543, 119], [543, 135], [539, 135]], "text": "o"}, {"id": 107, "box": [543, 119, 546, 135], "bndbox": [[543, 119], [546, 119], [546, 135], [543, 135]], "text": "r"}, {"id": 108, "box": [546, 119, 551, 135], "bndbox": [[546, 119], [551, 119], [551, 135], [546, 135]], "text": "t"}, {"id": 109, "box": [551, 119, 554, 135], "bndbox": [[551, 119], [554, 119], [554, 135], [551, 135]], "text": "h"}, {"id": 110, "box": [554, 119, 559, 135], "bndbox": [[554, 119], [559, 119], [559, 135], [554, 135]], "text": " "}, {"id": 111, "box": [559, 119, 563, 135], "bndbox": [[559, 119], [563, 119], [563, 135], [559, 135]], "text": "C"}, {"id": 112, "box": [563, 119, 568, 135], "bndbox": [[563, 119], [568, 119], [568, 135], [563, 135]], "text": "a"}, {"id": 113, "box": [568, 119, 572, 135], "bndbox": [[568, 119], [572, 119], [572, 135], [568, 135]], "text": "r"}, {"id": 114, "box": [572, 119, 576, 135], "bndbox": [[572, 119], [576, 119], [576, 135], [572, 135]], "text": "o"}, {"id": 115, "box": [576, 119, 580, 135], "bndbox": [[576, 119], [580, 119], [580, 135], [576, 135]], "text": "l"}, {"id": 116, "box": [580, 119, 583, 135], "bndbox": [[580, 119], [583, 119], [583, 135], [580, 135]], "text": "i"}, {"id": 117, "box": [583, 119, 587, 135], "bndbox": [[583, 119], [587, 119], [587, 135], [583, 135]], "text": "n"}, {"id": 118, "box": [587, 119, 591, 135], "bndbox": [[587, 119], [591, 119], [591, 135], [587, 135]], "text": "a"}, {"id": 119, "box": [591, 119, 595, 135], "bndbox": [[591, 119], [595, 119], [595, 135], [591, 135]], "text": " "}, {"id": 120, "box": [595, 119, 600, 135], "bndbox": [[595, 119], [600, 119], [600, 135], [595, 135]], "text": "2"}, {"id": 121, "box": [600, 119, 606, 135], "bndbox": [[600, 119], [606, 119], [606, 135], [600, 135]], "text": "7"}, {"id": 122, "box": [606, 119, 611, 135], "bndbox": [[606, 119], [611, 119], [611, 135], [606, 135]], "text": "4"}, {"id": 123, "box": [611, 119, 616, 135], "bndbox": [[611, 119], [616, 119], [616, 135], [611, 135]], "text": "2"}, {"id": 124, "box": [616, 119, 620, 135], "bndbox": [[616, 119], [620, 119], [620, 135], [616, 135]], "text": "0"}, {"id": 125, "box": [620, 119, 624, 135], "bndbox": [[620, 119], [624, 119], [624, 135], [620, 135]], "text": "-"}, {"id": 126, "box": [624, 119, 630, 135], "bndbox": [[624, 119], [630, 119], [630, 135], [624, 135]], "text": "1"}, {"id": 127, "box": [630, 119, 635, 135], "bndbox": [[630, 119], [635, 119], [635, 135], [630, 135]], "text": "6"}, {"id": 128, "box": [635, 119, 640, 135], "bndbox": [[635, 119], [640, 119], [640, 135], [635, 135]], "text": "8"}, {"id": 129, "box": [640, 119, 645, 136], "bndbox": [[640, 119], [645, 120], [645, 136], [640, 135]], "text": "8"}]}, {"id": 4, "box": [371, 225, 481, 240], "bndbox": [[371, 225], [481, 225], [481, 240], [371, 240]], "text": "VIA FACSIMILE", "words": [{"id": 130, "box": [371, 225, 381, 240], "bndbox": [[371, 225], [381, 225], [381, 240], [371, 240]], "text": "V"}, {"id": 131, "box": [381, 225, 388, 240], "bndbox": [[381, 225], [388, 225], [388, 240], [381, 240]], "text": "I"}, {"id": 132, "box": [388, 224, 396, 240], "bndbox": [[388, 225], [396, 224], [396, 240], [388, 240]], "text": "A"}, {"id": 133, "box": [396, 224, 404, 240], "bndbox": [[396, 224], [404, 224], [404, 240], [396, 240]], "text": " "}, {"id": 134, "box": [404, 224, 413, 240], "bndbox": [[404, 224], [413, 225], [413, 240], [404, 240]], "text": "F"}, {"id": 135, "box": [413, 225, 422, 240], "bndbox": [[413, 225], [422, 225], [422, 240], [413, 240]], "text": "A"}, {"id": 136, "box": [422, 225, 431, 240], "bndbox": [[422, 225], [431, 225], [431, 240], [422, 240]], "text": "C"}, {"id": 137, "box": [431, 225, 438, 240], "bndbox": [[431, 225], [438, 225], [438, 240], [431, 240]], "text": "S"}, {"id": 138, "box": [438, 225, 446, 240], "bndbox": [[438, 225], [446, 225], [446, 240], [438, 240]], "text": "I"}, {"id": 139, "box": [446, 225, 454, 240], "bndbox": [[446, 225], [454, 225], [454, 240], [446, 240]], "text": "M"}, {"id": 140, "box": [454, 225, 463, 240], "bndbox": [[454, 225], [463, 225], [463, 240], [454, 240]], "text": "I"}, {"id": 141, "box": [463, 225, 471, 240], "bndbox": [[463, 225], [471, 225], [471, 240], [463, 240]], "text": "L"}, {"id": 142, "box": [471, 225, 481, 240], "bndbox": [[471, 225], [481, 225], [481, 240], [471, 240]], "text": "E"}]}, {"id": 5, "box": [239, 295, 339, 315], "bndbox": [[239, 297], [339, 295], [339, 312], [239, 315]], "text": "919378-1001", "words": [{"id": 143, "box": [239, 296, 254, 315], "bndbox": [[239, 297], [254, 296], [254, 314], [239, 315]], "text": "9"}, {"id": 144, "box": [254, 296, 261, 314], "bndbox": [[254, 296], [261, 296], [261, 314], [254, 314]], "text": "1"}, {"id": 145, "box": [261, 296, 275, 314], "bndbox": [[261, 296], [275, 296], [275, 313], [261, 314]], "text": "9"}, {"id": 146, "box": [275, 296, 289, 313], "bndbox": [[275, 296], [289, 296], [289, 313], [275, 313]], "text": "3"}, {"id": 147, "box": [289, 295, 295, 313], "bndbox": [[289, 296], [295, 295], [295, 313], [289, 313]], "text": "7"}, {"id": 148, "box": [295, 295, 301, 313], "bndbox": [[295, 295], [301, 295], [301, 313], [295, 313]], "text": "8"}, {"id": 149, "box": [301, 295, 308, 313], "bndbox": [[301, 295], [308, 295], [308, 312], [301, 313]], "text": "-"}, {"id": 150, "box": [308, 295, 316, 312], "bndbox": [[308, 295], [316, 295], [316, 312], [308, 312]], "text": "1"}, {"id": 151, "box": [316, 295, 323, 312], "bndbox": [[316, 295], [323, 295], [323, 312], [316, 312]], "text": "0"}, {"id": 152, "box": [323, 295, 331, 312], "bndbox": [[323, 295], [331, 295], [331, 312], [323, 312]], "text": "0"}, {"id": 153, "box": [331, 295, 339, 312], "bndbox": [[331, 295], [339, 295], [339, 312], [331, 312]], "text": "1"}]}, {"id": 6, "box": [153, 322, 182, 339], "bndbox": [[153, 322], [182, 322], [182, 339], [153, 339]], "text": "TO:", "words": [{"id": 154, "box": [153, 322, 161, 339], "bndbox": [[153, 322], [161, 322], [161, 339], [153, 339]], "text": "T"}, {"id": 155, "box": [161, 322, 170, 339], "bndbox": [[161, 322], [170, 322], [170, 339], [161, 339]], "text": "O"}, {"id": 156, "box": [170, 322, 182, 339], "bndbox": [[170, 322], [182, 322], [182, 339], [170, 339]], "text": ":"}]}, {"id": 7, "box": [239, 320, 345, 333], "bndbox": [[239, 320], [345, 320], [345, 333], [239, 333]], "text": "Ron Goldbrenner", "words": [{"id": 157, "box": [239, 320, 247, 333], "bndbox": [[239, 320], [247, 320], [247, 333], [239, 333]], "text": "R"}, {"id": 158, "box": [247, 320, 254, 333], "bndbox": [[247, 320], [254, 320], [254, 333], [247, 333]], "text": "o"}, {"id": 159, "box": [254, 320, 260, 333], "bndbox": [[254, 320], [260, 320], [260, 333], [254, 333]], "text": "n"}, {"id": 160, "box": [260, 320, 269, 333], "bndbox": [[260, 320], [269, 320], [269, 333], [260, 333]], "text": " "}, {"id": 161, "box": [269, 320, 275, 333], "bndbox": [[269, 320], [275, 320], [275, 333], [269, 333]], "text": "G"}, {"id": 162, "box": [275, 320, 282, 333], "bndbox": [[275, 320], [282, 320], [282, 333], [275, 333]], "text": "o"}, {"id": 163, "box": [282, 320, 288, 333], "bndbox": [[282, 320], [288, 320], [288, 333], [282, 333]], "text": "l"}, {"id": 164, "box": [288, 320, 295, 333], "bndbox": [[288, 320], [295, 320], [295, 333], [288, 333]], "text": "d"}, {"id": 165, "box": [295, 320, 301, 333], "bndbox": [[295, 320], [301, 320], [301, 333], [295, 333]], "text": "b"}, {"id": 166, "box": [301, 320, 309, 333], "bndbox": [[301, 320], [309, 320], [309, 333], [301, 333]], "text": "r"}, {"id": 167, "box": [309, 320, 316, 333], "bndbox": [[309, 320], [316, 320], [316, 333], [309, 333]], "text": "e"}, {"id": 168, "box": [316, 320, 323, 333], "bndbox": [[316, 320], [323, 320], [323, 333], [316, 333]], "text": "n"}, {"id": 169, "box": [323, 320, 329, 333], "bndbox": [[323, 320], [329, 320], [329, 333], [323, 333]], "text": "n"}, {"id": 170, "box": [329, 320, 336, 333], "bndbox": [[329, 320], [336, 320], [336, 333], [329, 333]], "text": "e"}, {"id": 171, "box": [336, 320, 345, 333], "bndbox": [[336, 320], [345, 320], [345, 333], [336, 333]], "text": "r"}]}, {"id": 8, "box": [153, 350, 198, 365], "bndbox": [[153, 350], [198, 350], [198, 365], [153, 365]], "text": "FROM:", "words": [{"id": 172, "box": [153, 350, 163, 365], "bndbox": [[153, 350], [163, 350], [163, 365], [153, 365]], "text": "F"}, {"id": 173, "box": [163, 350, 170, 365], "bndbox": [[163, 350], [170, 350], [170, 365], [163, 365]], "text": "R"}, {"id": 174, "box": [170, 350, 179, 365], "bndbox": [[170, 350], [179, 350], [179, 365], [170, 365]], "text": "O"}, {"id": 175, "box": [179, 350, 188, 365], "bndbox": [[179, 350], [188, 350], [188, 365], [179, 365]], "text": "M"}, {"id": 176, "box": [188, 350, 198, 365], "bndbox": [[188, 350], [198, 350], [198, 365], [188, 365]], "text": ":"}]}, {"id": 9, "box": [239, 348, 326, 362], "bndbox": [[239, 348], [326, 348], [326, 362], [239, 362]], "text": "Becky Hayden", "words": [{"id": 177, "box": [239, 348, 247, 362], "bndbox": [[239, 348], [247, 348], [247, 362], [239, 362]], "text": "B"}, {"id": 178, "box": [247, 348, 255, 362], "bndbox": [[247, 348], [255, 348], [255, 362], [247, 362]], "text": "e"}, {"id": 179, "box": [255, 348, 261, 362], "bndbox": [[255, 348], [261, 348], [261, 362], [255, 362]], "text": "c"}, {"id": 180, "box": [261, 348, 267, 362], "bndbox": [[261, 348], [267, 348], [267, 362], [261, 362]], "text": "k"}, {"id": 181, "box": [267, 348, 274, 362], "bndbox": [[267, 348], [274, 348], [274, 362], [267, 362]], "text": "y"}, {"id": 182, "box": [274, 348, 282, 362], "bndbox": [[274, 348], [282, 348], [282, 362], [274, 362]], "text": " "}, {"id": 183, "box": [282, 348, 288, 362], "bndbox": [[282, 348], [288, 348], [288, 362], [282, 362]], "text": "H"}, {"id": 184, "box": [288, 348, 295, 362], "bndbox": [[288, 348], [295, 348], [295, 362], [288, 362]], "text": "a"}, {"id": 185, "box": [295, 348, 302, 362], "bndbox": [[295, 348], [302, 348], [302, 362], [295, 362]], "text": "y"}, {"id": 186, "box": [302, 348, 309, 362], "bndbox": [[302, 348], [309, 348], [309, 362], [302, 362]], "text": "d"}, {"id": 187, "box": [309, 348, 316, 362], "bndbox": [[309, 348], [316, 348], [316, 362], [309, 362]], "text": "e"}, {"id": 188, "box": [316, 348, 326, 362], "bndbox": [[316, 348], [326, 348], [326, 362], [316, 362]], "text": "n"}]}, {"id": 10, "box": [152, 378, 198, 393], "bndbox": [[152, 378], [198, 378], [198, 393], [152, 393]], "text": "DATE:", "words": [{"id": 189, "box": [152, 378, 163, 393], "bndbox": [[152, 378], [163, 378], [163, 393], [152, 393]], "text": "D"}, {"id": 190, "box": [163, 378, 172, 393], "bndbox": [[163, 378], [172, 378], [172, 393], [163, 393]], "text": "A"}, {"id": 191, "box": [172, 378, 180, 393], "bndbox": [[172, 378], [180, 378], [180, 393], [172, 393]], "text": "T"}, {"id": 192, "box": [180, 378, 189, 393], "bndbox": [[180, 378], [189, 378], [189, 393], [180, 393]], "text": "E"}, {"id": 193, "box": [189, 378, 198, 393], "bndbox": [[189, 378], [198, 378], [198, 393], [189, 393]], "text": ":"}]}, {"id": 11, "box": [239, 375, 332, 390], "bndbox": [[239, 375], [332, 375], [332, 390], [239, 390]], "text": "July 22,1993", "words": [{"id": 194, "box": [239, 375, 247, 390], "bndbox": [[239, 375], [247, 375], [247, 389], [239, 390]], "text": "J"}, {"id": 195, "box": [247, 375, 254, 390], "bndbox": [[247, 375], [254, 375], [254, 390], [247, 389]], "text": "u"}, {"id": 196, "box": [254, 375, 261, 390], "bndbox": [[254, 375], [261, 375], [261, 390], [254, 390]], "text": "l"}, {"id": 197, "box": [261, 375, 267, 390], "bndbox": [[261, 375], [267, 375], [267, 390], [261, 390]], "text": "y"}, {"id": 198, "box": [267, 375, 274, 390], "bndbox": [[267, 375], [274, 375], [274, 390], [267, 390]], "text": " "}, {"id": 199, "box": [274, 375, 281, 390], "bndbox": [[274, 375], [281, 375], [281, 390], [274, 390]], "text": "2"}, {"id": 200, "box": [281, 375, 289, 390], "bndbox": [[281, 375], [289, 375], [289, 390], [281, 390]], "text": "2"}, {"id": 201, "box": [289, 375, 299, 390], "bndbox": [[289, 375], [299, 375], [299, 390], [289, 390]], "text": ","}, {"id": 202, "box": [299, 375, 309, 390], "bndbox": [[299, 375], [309, 375], [309, 390], [299, 390]], "text": "1"}, {"id": 203, "box": [309, 375, 316, 390], "bndbox": [[309, 375], [316, 375], [316, 390], [309, 390]], "text": "9"}, {"id": 204, "box": [316, 375, 324, 390], "bndbox": [[316, 375], [324, 375], [324, 390], [316, 390]], "text": "9"}, {"id": 205, "box": [324, 375, 332, 390], "bndbox": [[324, 375], [332, 375], [332, 390], [324, 390]], "text": "3"}]}, {"id": 12, "box": [152, 418, 283, 433], "bndbox": [[152, 419], [283, 418], [283, 432], [152, 433]], "text": "NUMBER OF PAGES", "words": [{"id": 206, "box": [152, 418, 162, 433], "bndbox": [[152, 419], [162, 418], [162, 432], [152, 433]], "text": "N"}, {"id": 207, "box": [162, 418, 170, 432], "bndbox": [[162, 418], [170, 418], [170, 432], [162, 432]], "text": "U"}, {"id": 208, "box": [170, 418, 178, 432], "bndbox": [[170, 418], [178, 418], [178, 432], [170, 432]], "text": "M"}, {"id": 209, "box": [178, 418, 188, 432], "bndbox": [[178, 418], [188, 418], [188, 432], [178, 432]], "text": "B"}, {"id": 210, "box": [188, 418, 196, 432], "bndbox": [[188, 418], [196, 418], [196, 432], [188, 432]], "text": "E"}, {"id": 211, "box": [196, 418, 203, 432], "bndbox": [[196, 418], [203, 418], [203, 432], [196, 432]], "text": "R"}, {"id": 212, "box": [203, 418, 213, 432], "bndbox": [[203, 418], [213, 418], [213, 432], [203, 432]], "text": " "}, {"id": 213, "box": [213, 418, 222, 432], "bndbox": [[213, 418], [222, 418], [222, 432], [213, 432]], "text": "O"}, {"id": 214, "box": [222, 418, 229, 432], "bndbox": [[222, 418], [229, 418], [229, 432], [222, 432]], "text": "F"}, {"id": 215, "box": [229, 418, 238, 432], "bndbox": [[229, 418], [238, 418], [238, 432], [229, 432]], "text": " "}, {"id": 216, "box": [238, 418, 246, 432], "bndbox": [[238, 418], [246, 418], [246, 432], [238, 432]], "text": "P"}, {"id": 217, "box": [246, 418, 256, 432], "bndbox": [[246, 418], [256, 418], [256, 432], [246, 432]], "text": "A"}, {"id": 218, "box": [256, 418, 264, 432], "bndbox": [[256, 418], [264, 418], [264, 432], [256, 432]], "text": "G"}, {"id": 219, "box": [264, 418, 272, 432], "bndbox": [[264, 418], [272, 418], [272, 432], [264, 432]], "text": "E"}, {"id": 220, "box": [272, 418, 283, 432], "bndbox": [[272, 418], [283, 418], [283, 432], [272, 432]], "text": "S"}]}, {"id": 13, "box": [275, 413, 498, 431], "bndbox": [[275, 416], [498, 413], [498, 429], [275, 431]], "text": "S(INCLUDING COVER SHEET:", "words": [{"id": 221, "box": [275, 415, 289, 431], "bndbox": [[275, 416], [289, 415], [289, 430], [275, 431]], "text": "S"}, {"id": 222, "box": [289, 415, 306, 430], "bndbox": [[289, 415], [306, 415], [306, 430], [289, 430]], "text": "("}, {"id": 223, "box": [306, 415, 314, 430], "bndbox": [[306, 415], [314, 415], [314, 430], [306, 430]], "text": "I"}, {"id": 224, "box": [314, 415, 324, 430], "bndbox": [[314, 415], [324, 415], [324, 430], [314, 430]], "text": "N"}, {"id": 225, "box": [324, 415, 333, 430], "bndbox": [[324, 415], [333, 415], [333, 430], [324, 430]], "text": "C"}, {"id": 226, "box": [333, 415, 341, 430], "bndbox": [[333, 415], [341, 415], [341, 430], [333, 430]], "text": "L"}, {"id": 227, "box": [341, 415, 349, 430], "bndbox": [[341, 415], [349, 415], [349, 430], [341, 430]], "text": "U"}, {"id": 228, "box": [349, 414, 358, 430], "bndbox": [[349, 415], [358, 414], [358, 430], [349, 430]], "text": "D"}, {"id": 229, "box": [358, 414, 366, 430], "bndbox": [[358, 414], [366, 414], [366, 430], [358, 430]], "text": "I"}, {"id": 230, "box": [366, 414, 374, 430], "bndbox": [[366, 414], [374, 414], [374, 430], [366, 430]], "text": "N"}, {"id": 231, "box": [374, 414, 382, 430], "bndbox": [[374, 414], [382, 414], [382, 430], [374, 430]], "text": "G"}, {"id": 232, "box": [382, 414, 391, 430], "bndbox": [[382, 414], [391, 414], [391, 429], [382, 430]], "text": " "}, {"id": 233, "box": [391, 414, 399, 429], "bndbox": [[391, 414], [399, 414], [399, 429], [391, 429]], "text": "C"}, {"id": 234, "box": [399, 414, 407, 429], "bndbox": [[399, 414], [407, 414], [407, 429], [399, 429]], "text": "O"}, {"id": 235, "box": [407, 414, 415, 429], "bndbox": [[407, 414], [415, 414], [415, 429], [407, 429]], "text": "V"}, {"id": 236, "box": [415, 414, 423, 429], "bndbox": [[415, 414], [423, 414], [423, 429], [415, 429]], "text": "E"}, {"id": 237, "box": [423, 413, 431, 429], "bndbox": [[423, 414], [431, 413], [431, 429], [423, 429]], "text": "R"}, {"id": 238, "box": [431, 413, 440, 429], "bndbox": [[431, 413], [440, 413], [440, 429], [431, 429]], "text": " "}, {"id": 239, "box": [440, 413, 447, 429], "bndbox": [[440, 413], [447, 413], [447, 429], [440, 429]], "text": "S"}, {"id": 240, "box": [447, 413, 455, 429], "bndbox": [[447, 413], [455, 413], [455, 429], [447, 429]], "text": "H"}, {"id": 241, "box": [455, 413, 463, 429], "bndbox": [[455, 413], [463, 413], [463, 429], [455, 429]], "text": "E"}, {"id": 242, "box": [463, 413, 471, 429], "bndbox": [[463, 413], [471, 413], [471, 429], [463, 429]], "text": "E"}, {"id": 243, "box": [471, 413, 483, 429], "bndbox": [[471, 413], [483, 413], [483, 429], [471, 429]], "text": "T"}, {"id": 244, "box": [483, 413, 498, 429], "bndbox": [[483, 413], [498, 413], [498, 429], [483, 429]], "text": ":"}]}, {"id": 14, "box": [152, 442, 439, 463], "bndbox": [[152, 445], [439, 442], [439, 459], [152, 463]], "text": "OUR FAX NUMBER IS: (919) 373-6917", "words": [{"id": 245, "box": [152, 444, 162, 463], "bndbox": [[152, 445], [162, 444], [162, 462], [152, 463]], "text": "O"}, {"id": 246, "box": [162, 444, 169, 462], "bndbox": [[162, 444], [169, 444], [169, 462], [162, 462]], "text": "U"}, {"id": 247, "box": [169, 444, 177, 462], "bndbox": [[169, 444], [177, 444], [177, 462], [169, 462]], "text": "R"}, {"id": 248, "box": [177, 444, 186, 462], "bndbox": [[177, 444], [186, 444], [186, 462], [177, 462]], "text": " "}, {"id": 249, "box": [186, 444, 193, 462], "bndbox": [[186, 444], [193, 444], [193, 462], [186, 462]], "text": "F"}, {"id": 250, "box": [193, 444, 202, 462], "bndbox": [[193, 444], [202, 444], [202, 462], [193, 462]], "text": "A"}, {"id": 251, "box": [202, 444, 210, 462], "bndbox": [[202, 444], [210, 444], [210, 462], [202, 462]], "text": "X"}, {"id": 252, "box": [210, 444, 217, 462], "bndbox": [[210, 444], [217, 444], [217, 462], [210, 462]], "text": " "}, {"id": 253, "box": [217, 444, 226, 462], "bndbox": [[217, 444], [226, 444], [226, 461], [217, 462]], "text": "N"}, {"id": 254, "box": [226, 444, 234, 461], "bndbox": [[226, 444], [234, 444], [234, 461], [226, 461]], "text": "U"}, {"id": 255, "box": [234, 444, 241, 461], "bndbox": [[234, 444], [241, 444], [241, 461], [234, 461]], "text": "M"}, {"id": 256, "box": [241, 443, 250, 461], "bndbox": [[241, 444], [250, 443], [250, 461], [241, 461]], "text": "B"}, {"id": 257, "box": [250, 443, 259, 461], "bndbox": [[250, 443], [259, 443], [259, 461], [250, 461]], "text": "E"}, {"id": 258, "box": [259, 443, 267, 461], "bndbox": [[259, 443], [267, 443], [267, 461], [259, 461]], "text": "R"}, {"id": 259, "box": [267, 443, 276, 461], "bndbox": [[267, 443], [276, 443], [276, 461], [267, 461]], "text": " "}, {"id": 260, "box": [276, 443, 283, 461], "bndbox": [[276, 443], [283, 443], [283, 461], [276, 461]], "text": "I"}, {"id": 261, "box": [283, 443, 292, 461], "bndbox": [[283, 443], [292, 443], [292, 461], [283, 461]], "text": "S"}, {"id": 262, "box": [292, 443, 302, 461], "bndbox": [[292, 443], [302, 443], [302, 460], [292, 461]], "text": ":"}, {"id": 263, "box": [302, 443, 314, 460], "bndbox": [[302, 443], [314, 443], [314, 460], [302, 460]], "text": " "}, {"id": 264, "box": [314, 443, 325, 460], "bndbox": [[314, 443], [325, 443], [325, 460], [314, 460]], "text": "("}, {"id": 265, "box": [325, 443, 334, 460], "bndbox": [[325, 443], [334, 443], [334, 460], [325, 460]], "text": "9"}, {"id": 266, "box": [334, 443, 343, 460], "bndbox": [[334, 443], [343, 443], [343, 460], [334, 460]], "text": "1"}, {"id": 267, "box": [343, 442, 352, 460], "bndbox": [[343, 443], [352, 442], [352, 460], [343, 460]], "text": "9"}, {"id": 268, "box": [352, 442, 359, 460], "bndbox": [[352, 442], [359, 442], [359, 460], [352, 460]], "text": ")"}, {"id": 269, "box": [359, 442, 367, 460], "bndbox": [[359, 442], [367, 442], [367, 460], [359, 460]], "text": " "}, {"id": 270, "box": [367, 442, 376, 460], "bndbox": [[367, 442], [376, 442], [376, 459], [367, 460]], "text": "3"}, {"id": 271, "box": [376, 442, 385, 459], "bndbox": [[376, 442], [385, 442], [385, 459], [376, 459]], "text": "7"}, {"id": 272, "box": [385, 442, 392, 459], "bndbox": [[385, 442], [392, 442], [392, 459], [385, 459]], "text": "3"}, {"id": 273, "box": [392, 442, 401, 459], "bndbox": [[392, 442], [401, 442], [401, 459], [392, 459]], "text": "-"}, {"id": 274, "box": [401, 442, 412, 459], "bndbox": [[401, 442], [412, 442], [412, 459], [401, 459]], "text": "6"}, {"id": 275, "box": [412, 442, 419, 459], "bndbox": [[412, 442], [419, 442], [419, 459], [412, 459]], "text": "9"}, {"id": 276, "box": [419, 442, 427, 459], "bndbox": [[419, 442], [427, 442], [427, 459], [419, 459]], "text": "1"}, {"id": 277, "box": [427, 442, 439, 459], "bndbox": [[427, 442], [439, 442], [439, 459], [427, 459]], "text": "7"}]}, {"id": 15, "box": [153, 566, 480, 585], "bndbox": [[153, 569], [480, 566], [480, 582], [153, 585]], "text": "IF YOU DO NOT RECEIVE ANY OF THE PAGES,", "words": [{"id": 278, "box": [153, 568, 163, 585], "bndbox": [[153, 569], [163, 568], [163, 584], [153, 585]], "text": "I"}, {"id": 279, "box": [163, 568, 170, 584], "bndbox": [[163, 568], [170, 568], [170, 584], [163, 584]], "text": "F"}, {"id": 280, "box": [170, 568, 179, 584], "bndbox": [[170, 568], [179, 568], [179, 584], [170, 584]], "text": " "}, {"id": 281, "box": [179, 568, 187, 584], "bndbox": [[179, 568], [187, 568], [187, 584], [179, 584]], "text": "Y"}, {"id": 282, "box": [187, 568, 195, 584], "bndbox": [[187, 568], [195, 568], [195, 584], [187, 584]], "text": "O"}, {"id": 283, "box": [195, 568, 203, 584], "bndbox": [[195, 568], [203, 568], [203, 584], [195, 584]], "text": "U"}, {"id": 284, "box": [203, 568, 214, 584], "bndbox": [[203, 568], [214, 568], [214, 584], [203, 584]], "text": " "}, {"id": 285, "box": [214, 568, 222, 584], "bndbox": [[214, 568], [222, 568], [222, 584], [214, 584]], "text": "D"}, {"id": 286, "box": [222, 568, 228, 584], "bndbox": [[222, 568], [228, 568], [228, 584], [222, 584]], "text": "O"}, {"id": 287, "box": [228, 568, 239, 584], "bndbox": [[228, 568], [239, 568], [239, 584], [228, 584]], "text": " "}, {"id": 288, "box": [239, 568, 246, 584], "bndbox": [[239, 568], [246, 568], [246, 584], [239, 584]], "text": "N"}, {"id": 289, "box": [246, 568, 254, 584], "bndbox": [[246, 568], [254, 568], [254, 584], [246, 584]], "text": "O"}, {"id": 290, "box": [254, 568, 262, 584], "bndbox": [[254, 568], [262, 568], [262, 584], [254, 584]], "text": "T"}, {"id": 291, "box": [262, 567, 272, 584], "bndbox": [[262, 568], [272, 567], [272, 583], [262, 584]], "text": " "}, {"id": 292, "box": [272, 567, 280, 583], "bndbox": [[272, 567], [280, 567], [280, 583], [272, 583]], "text": "R"}, {"id": 293, "box": [280, 567, 288, 583], "bndbox": [[280, 567], [288, 567], [288, 583], [280, 583]], "text": "E"}, {"id": 294, "box": [288, 567, 296, 583], "bndbox": [[288, 567], [296, 567], [296, 583], [288, 583]], "text": "C"}, {"id": 295, "box": [296, 567, 304, 583], "bndbox": [[296, 567], [304, 567], [304, 583], [296, 583]], "text": "E"}, {"id": 296, "box": [304, 567, 313, 583], "bndbox": [[304, 567], [313, 567], [313, 583], [304, 583]], "text": "I"}, {"id": 297, "box": [313, 567, 321, 583], "bndbox": [[313, 567], [321, 567], [321, 583], [313, 583]], "text": "V"}, {"id": 298, "box": [321, 567, 328, 583], "bndbox": [[321, 567], [328, 567], [328, 583], [321, 583]], "text": "E"}, {"id": 299, "box": [328, 567, 339, 583], "bndbox": [[328, 567], [339, 567], [339, 583], [328, 583]], "text": " "}, {"id": 300, "box": [339, 567, 347, 583], "bndbox": [[339, 567], [347, 567], [347, 583], [339, 583]], "text": "A"}, {"id": 301, "box": [347, 567, 355, 583], "bndbox": [[347, 567], [355, 567], [355, 583], [347, 583]], "text": "N"}, {"id": 302, "box": [355, 567, 361, 583], "bndbox": [[355, 567], [361, 567], [361, 583], [355, 583]], "text": "Y"}, {"id": 303, "box": [361, 567, 371, 583], "bndbox": [[361, 567], [371, 567], [371, 583], [361, 583]], "text": " "}, {"id": 304, "box": [371, 566, 378, 583], "bndbox": [[371, 567], [378, 566], [378, 582], [371, 583]], "text": "O"}, {"id": 305, "box": [378, 566, 386, 582], "bndbox": [[378, 566], [386, 566], [386, 582], [378, 582]], "text": "F"}, {"id": 306, "box": [386, 566, 396, 582], "bndbox": [[386, 566], [396, 566], [396, 582], [386, 582]], "text": " "}, {"id": 307, "box": [396, 566, 402, 582], "bndbox": [[396, 566], [402, 566], [402, 582], [396, 582]], "text": "T"}, {"id": 308, "box": [402, 566, 412, 582], "bndbox": [[402, 566], [412, 566], [412, 582], [402, 582]], "text": "H"}, {"id": 309, "box": [412, 566, 420, 582], "bndbox": [[412, 566], [420, 566], [420, 582], [412, 582]], "text": "E"}, {"id": 310, "box": [420, 566, 429, 582], "bndbox": [[420, 566], [429, 566], [429, 582], [420, 582]], "text": " "}, {"id": 311, "box": [429, 566, 437, 582], "bndbox": [[429, 566], [437, 566], [437, 582], [429, 582]], "text": "P"}, {"id": 312, "box": [437, 566, 445, 582], "bndbox": [[437, 566], [445, 566], [445, 582], [437, 582]], "text": "A"}, {"id": 313, "box": [445, 566, 453, 582], "bndbox": [[445, 566], [453, 566], [453, 582], [445, 582]], "text": "G"}, {"id": 314, "box": [453, 566, 462, 582], "bndbox": [[453, 566], [462, 566], [462, 582], [453, 582]], "text": "E"}, {"id": 315, "box": [462, 566, 472, 582], "bndbox": [[462, 566], [472, 566], [472, 582], [462, 582]], "text": "S"}, {"id": 316, "box": [472, 566, 480, 582], "bndbox": [[472, 566], [480, 566], [480, 582], [472, 582]], "text": ","}]}, {"id": 16, "box": [154, 584, 250, 598], "bndbox": [[154, 584], [250, 584], [250, 598], [154, 598]], "text": "PLEASE CALL", "words": [{"id": 317, "box": [154, 584, 163, 598], "bndbox": [[154, 584], [163, 584], [163, 598], [154, 598]], "text": "P"}, {"id": 318, "box": [163, 584, 171, 598], "bndbox": [[163, 584], [171, 584], [171, 598], [163, 598]], "text": "L"}, {"id": 319, "box": [171, 584, 179, 598], "bndbox": [[171, 584], [179, 584], [179, 598], [171, 598]], "text": "E"}, {"id": 320, "box": [179, 584, 187, 598], "bndbox": [[179, 584], [187, 584], [187, 598], [179, 598]], "text": "A"}, {"id": 321, "box": [187, 584, 197, 598], "bndbox": [[187, 584], [197, 584], [197, 598], [187, 598]], "text": "S"}, {"id": 322, "box": [197, 584, 204, 598], "bndbox": [[197, 584], [204, 584], [204, 598], [197, 598]], "text": "E"}, {"id": 323, "box": [204, 584, 213, 598], "bndbox": [[204, 584], [213, 584], [213, 598], [204, 598]], "text": " "}, {"id": 324, "box": [213, 584, 221, 598], "bndbox": [[213, 584], [221, 584], [221, 598], [213, 598]], "text": "C"}, {"id": 325, "box": [221, 584, 230, 598], "bndbox": [[221, 584], [230, 584], [230, 598], [221, 598]], "text": "A"}, {"id": 326, "box": [230, 584, 238, 598], "bndbox": [[230, 584], [238, 584], [238, 598], [230, 598]], "text": "L"}, {"id": 327, "box": [238, 584, 250, 598], "bndbox": [[238, 584], [250, 584], [250, 598], [238, 598]], "text": "L"}]}, {"id": 17, "box": [153, 597, 228, 611], "bndbox": [[153, 597], [228, 597], [228, 611], [153, 611]], "text": "AT919", "words": [{"id": 328, "box": [153, 597, 162, 611], "bndbox": [[153, 597], [162, 597], [162, 611], [153, 611]], "text": "A"}, {"id": 329, "box": [162, 597, 178, 611], "bndbox": [[162, 597], [178, 597], [178, 611], [162, 611]], "text": "T"}, {"id": 330, "box": [178, 597, 196, 611], "bndbox": [[178, 597], [196, 597], [196, 611], [178, 611]], "text": "9"}, {"id": 331, "box": [196, 597, 205, 611], "bndbox": [[196, 597], [205, 597], [205, 611], [196, 611]], "text": "1"}, {"id": 332, "box": [205, 597, 228, 611], "bndbox": [[205, 597], [228, 597], [228, 611], [205, 611]], "text": "9"}]}, {"id": 18, "box": [411, 593, 641, 610], "bndbox": [[411, 596], [641, 593], [641, 607], [411, 610]], "text": "AT THE GREENSBORO BRANCH AS", "words": [{"id": 333, "box": [411, 595, 422, 610], "bndbox": [[411, 596], [422, 595], [422, 609], [411, 610]], "text": "A"}, {"id": 334, "box": [422, 595, 429, 609], "bndbox": [[422, 595], [429, 595], [429, 609], [422, 609]], "text": "T"}, {"id": 335, "box": [429, 595, 439, 609], "bndbox": [[429, 595], [439, 595], [439, 609], [429, 609]], "text": " "}, {"id": 336, "box": [439, 595, 446, 609], "bndbox": [[439, 595], [446, 595], [446, 609], [439, 609]], "text": "T"}, {"id": 337, "box": [446, 595, 454, 609], "bndbox": [[446, 595], [454, 595], [454, 609], [446, 609]], "text": "H"}, {"id": 338, "box": [454, 595, 462, 609], "bndbox": [[454, 595], [462, 595], [462, 609], [454, 609]], "text": "E"}, {"id": 339, "box": [462, 595, 473, 609], "bndbox": [[462, 595], [473, 595], [473, 609], [462, 609]], "text": " "}, {"id": 340, "box": [473, 595, 481, 609], "bndbox": [[473, 595], [481, 595], [481, 609], [473, 609]], "text": "G"}, {"id": 341, "box": [481, 594, 489, 609], "bndbox": [[481, 595], [489, 594], [489, 608], [481, 609]], "text": "R"}, {"id": 342, "box": [489, 594, 497, 608], "bndbox": [[489, 594], [497, 594], [497, 608], [489, 608]], "text": "E"}, {"id": 343, "box": [497, 594, 506, 608], "bndbox": [[497, 594], [506, 594], [506, 608], [497, 608]], "text": "E"}, {"id": 344, "box": [506, 594, 515, 608], "bndbox": [[506, 594], [515, 594], [515, 608], [506, 608]], "text": "N"}, {"id": 345, "box": [515, 594, 523, 608], "bndbox": [[515, 594], [523, 594], [523, 608], [515, 608]], "text": "S"}, {"id": 346, "box": [523, 594, 531, 608], "bndbox": [[523, 594], [531, 594], [531, 608], [523, 608]], "text": "B"}, {"id": 347, "box": [531, 594, 540, 608], "bndbox": [[531, 594], [540, 594], [540, 608], [531, 608]], "text": "O"}, {"id": 348, "box": [540, 594, 548, 608], "bndbox": [[540, 594], [548, 594], [548, 608], [540, 608]], "text": "R"}, {"id": 349, "box": [548, 594, 556, 608], "bndbox": [[548, 594], [556, 594], [556, 608], [548, 608]], "text": "O"}, {"id": 350, "box": [556, 593, 565, 608], "bndbox": [[556, 594], [565, 593], [565, 607], [556, 608]], "text": " "}, {"id": 351, "box": [565, 593, 574, 607], "bndbox": [[565, 593], [574, 593], [574, 607], [565, 607]], "text": "B"}, {"id": 352, "box": [574, 593, 582, 607], "bndbox": [[574, 593], [582, 593], [582, 607], [574, 607]], "text": "R"}, {"id": 353, "box": [582, 593, 590, 607], "bndbox": [[582, 593], [590, 593], [590, 607], [582, 607]], "text": "A"}, {"id": 354, "box": [590, 593, 599, 607], "bndbox": [[590, 593], [599, 593], [599, 607], [590, 607]], "text": "N"}, {"id": 355, "box": [599, 593, 608, 607], "bndbox": [[599, 593], [608, 593], [608, 607], [599, 607]], "text": "C"}, {"id": 356, "box": [608, 593, 615, 607], "bndbox": [[608, 593], [615, 593], [615, 607], [608, 607]], "text": "H"}, {"id": 357, "box": [615, 593, 625, 607], "bndbox": [[615, 593], [625, 593], [625, 607], [615, 607]], "text": " "}, {"id": 358, "box": [625, 593, 633, 607], "bndbox": [[625, 593], [633, 593], [633, 607], [625, 607]], "text": "A"}, {"id": 359, "box": [633, 593, 641, 607], "bndbox": [[633, 593], [641, 593], [641, 607], [633, 607]], "text": "S"}]}, {"id": 19, "box": [154, 611, 296, 626], "bndbox": [[154, 611], [296, 611], [296, 626], [154, 626]], "text": "SOON AS POSSIBLE.", "words": [{"id": 360, "box": [154, 611, 162, 626], "bndbox": [[154, 611], [162, 611], [162, 626], [154, 626]], "text": "S"}, {"id": 361, "box": [162, 611, 171, 626], "bndbox": [[162, 611], [171, 611], [171, 626], [162, 626]], "text": "O"}, {"id": 362, "box": [171, 611, 178, 626], "bndbox": [[171, 611], [178, 611], [178, 626], [171, 626]], "text": "O"}, {"id": 363, "box": [178, 611, 186, 626], "bndbox": [[178, 611], [186, 611], [186, 626], [178, 626]], "text": "N"}, {"id": 364, "box": [186, 611, 196, 626], "bndbox": [[186, 611], [196, 611], [196, 626], [186, 626]], "text": " "}, {"id": 365, "box": [196, 611, 205, 626], "bndbox": [[196, 611], [205, 611], [205, 626], [196, 626]], "text": "A"}, {"id": 366, "box": [205, 611, 213, 626], "bndbox": [[205, 611], [213, 611], [213, 626], [205, 626]], "text": "S"}, {"id": 367, "box": [213, 611, 221, 626], "bndbox": [[213, 611], [221, 611], [221, 626], [213, 626]], "text": " "}, {"id": 368, "box": [221, 611, 229, 626], "bndbox": [[221, 611], [229, 611], [229, 626], [221, 626]], "text": "P"}, {"id": 369, "box": [229, 611, 238, 626], "bndbox": [[229, 611], [238, 611], [238, 626], [229, 626]], "text": "O"}, {"id": 370, "box": [238, 611, 246, 626], "bndbox": [[238, 611], [246, 611], [246, 626], [238, 626]], "text": "S"}, {"id": 371, "box": [246, 611, 254, 626], "bndbox": [[246, 611], [254, 611], [254, 626], [246, 626]], "text": "S"}, {"id": 372, "box": [254, 611, 263, 626], "bndbox": [[254, 611], [263, 611], [263, 626], [254, 626]], "text": "I"}, {"id": 373, "box": [263, 611, 271, 626], "bndbox": [[263, 611], [271, 611], [271, 626], [263, 626]], "text": "B"}, {"id": 374, "box": [271, 611, 279, 626], "bndbox": [[271, 611], [279, 611], [279, 626], [271, 626]], "text": "L"}, {"id": 375, "box": [279, 611, 288, 626], "bndbox": [[279, 611], [288, 611], [288, 626], [279, 626]], "text": "E"}, {"id": 376, "box": [288, 611, 296, 626], "bndbox": [[288, 611], [296, 611], [296, 626], [288, 626]], "text": "."}]}, {"id": 20, "box": [152, 638, 237, 652], "bndbox": [[152, 638], [237, 638], [237, 652], [152, 652]], "text": "THANK YOU.", "words": [{"id": 377, "box": [152, 638, 162, 652], "bndbox": [[152, 638], [162, 638], [162, 652], [152, 652]], "text": "T"}, {"id": 378, "box": [162, 638, 172, 652], "bndbox": [[162, 638], [172, 638], [172, 652], [162, 652]], "text": "H"}, {"id": 379, "box": [172, 638, 180, 652], "bndbox": [[172, 638], [180, 638], [180, 652], [172, 652]], "text": "A"}, {"id": 380, "box": [180, 638, 188, 652], "bndbox": [[180, 638], [188, 638], [188, 652], [180, 652]], "text": "N"}, {"id": 381, "box": [188, 638, 196, 652], "bndbox": [[188, 638], [196, 638], [196, 652], [188, 652]], "text": "K"}, {"id": 382, "box": [196, 638, 206, 652], "bndbox": [[196, 638], [206, 638], [206, 652], [196, 652]], "text": " "}, {"id": 383, "box": [206, 638, 214, 652], "bndbox": [[206, 638], [214, 638], [214, 652], [206, 652]], "text": "Y"}, {"id": 384, "box": [214, 638, 222, 652], "bndbox": [[214, 638], [222, 638], [222, 652], [214, 652]], "text": "O"}, {"id": 385, "box": [222, 638, 231, 652], "bndbox": [[222, 638], [231, 638], [231, 652], [222, 652]], "text": "U"}, {"id": 386, "box": [231, 638, 237, 652], "bndbox": [[231, 638], [237, 638], [237, 652], [231, 652]], "text": "."}]}, {"id": 21, "box": [692, 758, 720, 835], "bndbox": [[701, 758], [720, 760], [711, 835], [692, 833]], "text": "92327794", "words": [{"id": 387, "box": [692, 758, 704, 833], "bndbox": [[701, 758], [704, 758], [695, 833], [692, 833]], "text": "9"}, {"id": 388, "box": [695, 758, 706, 833], "bndbox": [[704, 758], [706, 758], [697, 833], [695, 833]], "text": "2"}, {"id": 389, "box": [697, 758, 708, 833], "bndbox": [[706, 758], [708, 758], [699, 833], [697, 833]], "text": "3"}, {"id": 390, "box": [699, 758, 710, 834], "bndbox": [[708, 758], [710, 759], [701, 834], [699, 833]], "text": "2"}, {"id": 391, "box": [701, 759, 712, 834], "bndbox": [[710, 759], [712, 759], [703, 834], [701, 834]], "text": "7"}, {"id": 392, "box": [703, 759, 714, 834], "bndbox": [[712, 759], [714, 759], [705, 834], [703, 834]], "text": "7"}, {"id": 393, "box": [705, 759, 716, 834], "bndbox": [[714, 759], [716, 759], [707, 834], [705, 834]], "text": "9"}, {"id": 394, "box": [707, 759, 720, 835], "bndbox": [[716, 759], [720, 760], [711, 835], [707, 834]], "text": "4"}]}], "uid": "92327794", "label_entities": [{"entity_id": 0, "label": "question", "word_idx": [154, 155, 156]}, {"entity_id": 1, "label": "question", "word_idx": [172, 173, 174, 175, 176]}, {"entity_id": 2, "label": "question", "word_idx": [189, 190, 191, 192, 193]}, {"entity_id": 9, "label": "header", "word_idx": [130, 131, 132, 133, 134, 135, 136, 137, 138, 139, 140, 141, 142]}, {"entity_id": 10, "label": "answer", "word_idx": [143, 144, 145, 146, 147, 148, 149, 150, 151, 152, 153, 157, 158, 159, 160, 161, 162, 163, 164, 165, 166, 167, 168, 169, 170, 171]}, {"entity_id": 11, "label": "answer", "word_idx": [177, 178, 179, 180, 181, 182, 183, 184, 185, 186, 187, 188]}, {"entity_id": 12, "label": "answer", "word_idx": [194, 195, 196, 197, 198, 199, 200, 201, 202, 203, 204, 205]}, {"entity_id": 13, "label": "question", "word_idx": [206, 207, 208, 209, 210, 211, 212, 213, 214, 215, 216, 217, 218, 219, 220, 221, 222, 223, 224, 225, 226, 227, 228, 229, 230, 231, 232, 233, 234, 235, 236, 237, 238, 239, 240, 241, 242, 243, 244]}, {"entity_id": 16, "label": "question", "word_idx": [278, 279, 280, 281, 282, 283, 284, 285, 286, 287, 288, 289, 290, 291, 292, 293, 294, 295, 296, 297, 298, 299, 300, 301, 302, 303, 304, 305, 306, 307, 308, 309, 310, 311, 312, 313, 314, 315, 316, 317, 318, 319, 320, 321, 322, 323, 324, 325, 326, 327]}, {"entity_id": 17, "label": "question", "word_idx": [328, 329, 330, 331, 332, 333, 334, 335, 336, 337, 338, 339, 340, 341, 342, 343, 344, 345, 346, 347, 348, 349, 350, 351, 352, 353, 354, 355, 356, 357, 358, 359, 360, 361, 362, 363, 364, 365, 366, 367, 368, 369, 370, 371, 372, 373, 374, 375, 376]}, {"entity_id": 14, "label": "question", "word_idx": [245, 246, 247, 248, 249, 250, 251, 252, 253, 254, 255, 256, 257, 258, 259, 260, 261, 262]}, {"entity_id": 15, "label": "answer", "word_idx": [264, 265, 266, 267, 268, 269, 270, 271, 272, 273, 274, 275, 276, 277]}], "label_linkings": [[0, 10], [1, 11], [2, 12], [14, 15]]}